
{"items":[{"name":"ACadSharp","href":"ACadSharp.html","topicHref":"ACadSharp.html","topicUid":"ACadSharp","type":"Namespace","items":[{"name":"ACadVersion","href":"ACadSharp.ACadVersion.html","topicHref":"ACadSharp.ACadVersion.html","topicUid":"ACadSharp.ACadVersion","type":"Enum"},{"name":"CadDocument","href":"ACadSharp.CadDocument.html","topicHref":"ACadSharp.CadDocument.html","topicUid":"ACadSharp.CadDocument","type":"Class"},{"name":"CadObject","href":"ACadSharp.CadObject.html","topicHref":"ACadSharp.CadObject.html","topicUid":"ACadSharp.CadObject","type":"Class"},{"name":"CadObjectCollection<T>","href":"ACadSharp.CadObjectCollection-1.html","topicHref":"ACadSharp.CadObjectCollection-1.html","topicUid":"ACadSharp.CadObjectCollection`1","type":"Class"},{"name":"CadSummaryInfo","href":"ACadSharp.CadSummaryInfo.html","topicHref":"ACadSharp.CadSummaryInfo.html","topicUid":"ACadSharp.CadSummaryInfo","type":"Class"},{"name":"CadSystemVariable","href":"ACadSharp.CadSystemVariable.html","topicHref":"ACadSharp.CadSystemVariable.html","topicUid":"ACadSharp.CadSystemVariable","type":"Class"},{"name":"CadValue","href":"ACadSharp.CadValue.html","topicHref":"ACadSharp.CadValue.html","topicUid":"ACadSharp.CadValue","type":"Class"},{"name":"CadValueType","href":"ACadSharp.CadValueType.html","topicHref":"ACadSharp.CadValueType.html","topicUid":"ACadSharp.CadValueType","type":"Enum"},{"name":"CadValueUnitType","href":"ACadSharp.CadValueUnitType.html","topicHref":"ACadSharp.CadValueUnitType.html","topicUid":"ACadSharp.CadValueUnitType","type":"Enum"},{"name":"CollectionChangedEventArgs","href":"ACadSharp.CollectionChangedEventArgs.html","topicHref":"ACadSharp.CollectionChangedEventArgs.html","topicUid":"ACadSharp.CollectionChangedEventArgs","type":"Class"},{"name":"Color","href":"ACadSharp.Color.html","topicHref":"ACadSharp.Color.html","topicUid":"ACadSharp.Color","type":"Struct"},{"name":"DwgPreview","href":"ACadSharp.DwgPreview.html","topicHref":"ACadSharp.DwgPreview.html","topicUid":"ACadSharp.DwgPreview","type":"Class"},{"name":"DwgPreview.PreviewType","href":"ACadSharp.DwgPreview.PreviewType.html","topicHref":"ACadSharp.DwgPreview.PreviewType.html","topicUid":"ACadSharp.DwgPreview.PreviewType","type":"Enum"},{"name":"DwgReferenceType","href":"ACadSharp.DwgReferenceType.html","topicHref":"ACadSharp.DwgReferenceType.html","topicUid":"ACadSharp.DwgReferenceType","type":"Enum"},{"name":"DxfClassMap","href":"ACadSharp.DxfClassMap.html","topicHref":"ACadSharp.DxfClassMap.html","topicUid":"ACadSharp.DxfClassMap","type":"Class"},{"name":"DxfCode","href":"ACadSharp.DxfCode.html","topicHref":"ACadSharp.DxfCode.html","topicUid":"ACadSharp.DxfCode","type":"Enum"},{"name":"DxfFileToken","href":"ACadSharp.DxfFileToken.html","topicHref":"ACadSharp.DxfFileToken.html","topicUid":"ACadSharp.DxfFileToken","type":"Class"},{"name":"DxfMap","href":"ACadSharp.DxfMap.html","topicHref":"ACadSharp.DxfMap.html","topicUid":"ACadSharp.DxfMap","type":"Class"},{"name":"DxfMapBase","href":"ACadSharp.DxfMapBase.html","topicHref":"ACadSharp.DxfMapBase.html","topicUid":"ACadSharp.DxfMapBase","type":"Class"},{"name":"DxfProperty","href":"ACadSharp.DxfProperty.html","topicHref":"ACadSharp.DxfProperty.html","topicUid":"ACadSharp.DxfProperty","type":"Class"},{"name":"DxfPropertyBase<T>","href":"ACadSharp.DxfPropertyBase-1.html","topicHref":"ACadSharp.DxfPropertyBase-1.html","topicUid":"ACadSharp.DxfPropertyBase`1","type":"Class"},{"name":"DxfReferenceType","href":"ACadSharp.DxfReferenceType.html","topicHref":"ACadSharp.DxfReferenceType.html","topicUid":"ACadSharp.DxfReferenceType","type":"Enum"},{"name":"DxfSubclassMarker","href":"ACadSharp.DxfSubclassMarker.html","topicHref":"ACadSharp.DxfSubclassMarker.html","topicUid":"ACadSharp.DxfSubclassMarker","type":"Class"},{"name":"FlowDirectionType","href":"ACadSharp.FlowDirectionType.html","topicHref":"ACadSharp.FlowDirectionType.html","topicUid":"ACadSharp.FlowDirectionType","type":"Enum"},{"name":"GroupCodeValue","href":"ACadSharp.GroupCodeValue.html","topicHref":"ACadSharp.GroupCodeValue.html","topicUid":"ACadSharp.GroupCodeValue","type":"Class"},{"name":"GroupCodeValueType","href":"ACadSharp.GroupCodeValueType.html","topicHref":"ACadSharp.GroupCodeValueType.html","topicUid":"ACadSharp.GroupCodeValueType","type":"Enum"},{"name":"ICadCollection<T>","href":"ACadSharp.ICadCollection-1.html","topicHref":"ACadSharp.ICadCollection-1.html","topicUid":"ACadSharp.ICadCollection`1","type":"Interface"},{"name":"IHandledCadObject","href":"ACadSharp.IHandledCadObject.html","topicHref":"ACadSharp.IHandledCadObject.html","topicUid":"ACadSharp.IHandledCadObject","type":"Interface"},{"name":"INamedCadObject","href":"ACadSharp.INamedCadObject.html","topicHref":"ACadSharp.INamedCadObject.html","topicUid":"ACadSharp.INamedCadObject","type":"Interface"},{"name":"IObservableCadCollection<T>","href":"ACadSharp.IObservableCadCollection-1.html","topicHref":"ACadSharp.IObservableCadCollection-1.html","topicUid":"ACadSharp.IObservableCadCollection`1","type":"Interface"},{"name":"IProxy","href":"ACadSharp.IProxy.html","topicHref":"ACadSharp.IProxy.html","topicUid":"ACadSharp.IProxy","type":"Interface"},{"name":"ISeqendCollection","href":"ACadSharp.ISeqendCollection.html","topicHref":"ACadSharp.ISeqendCollection.html","topicUid":"ACadSharp.ISeqendCollection","type":"Interface"},{"name":"LineSpacingStyle","href":"ACadSharp.LineSpacingStyle.html","topicHref":"ACadSharp.LineSpacingStyle.html","topicUid":"ACadSharp.LineSpacingStyle","type":"Enum"},{"name":"LineWeightType","href":"ACadSharp.LineWeightType.html","topicHref":"ACadSharp.LineWeightType.html","topicUid":"ACadSharp.LineWeightType","type":"Enum"},{"name":"MultiLeaderPathType","href":"ACadSharp.MultiLeaderPathType.html","topicHref":"ACadSharp.MultiLeaderPathType.html","topicUid":"ACadSharp.MultiLeaderPathType","type":"Enum"},{"name":"ObjectType","href":"ACadSharp.ObjectType.html","topicHref":"ACadSharp.ObjectType.html","topicUid":"ACadSharp.ObjectType","type":"Enum"},{"name":"OnNameChangedArgs","href":"ACadSharp.OnNameChangedArgs.html","topicHref":"ACadSharp.OnNameChangedArgs.html","topicUid":"ACadSharp.OnNameChangedArgs","type":"Class"},{"name":"OrthographicType","href":"ACadSharp.OrthographicType.html","topicHref":"ACadSharp.OrthographicType.html","topicUid":"ACadSharp.OrthographicType","type":"Enum"},{"name":"RenderMode","href":"ACadSharp.RenderMode.html","topicHref":"ACadSharp.RenderMode.html","topicUid":"ACadSharp.RenderMode","type":"Enum"},{"name":"SeqendCollection<T>","href":"ACadSharp.SeqendCollection-1.html","topicHref":"ACadSharp.SeqendCollection-1.html","topicUid":"ACadSharp.SeqendCollection`1","type":"Class"},{"name":"TextAlignmentType","href":"ACadSharp.TextAlignmentType.html","topicHref":"ACadSharp.TextAlignmentType.html","topicUid":"ACadSharp.TextAlignmentType","type":"Enum"},{"name":"TextAngleType","href":"ACadSharp.TextAngleType.html","topicHref":"ACadSharp.TextAngleType.html","topicUid":"ACadSharp.TextAngleType","type":"Enum"},{"name":"TextAttachmentDirectionType","href":"ACadSharp.TextAttachmentDirectionType.html","topicHref":"ACadSharp.TextAttachmentDirectionType.html","topicUid":"ACadSharp.TextAttachmentDirectionType","type":"Enum"},{"name":"TextAttachmentPointType","href":"ACadSharp.TextAttachmentPointType.html","topicHref":"ACadSharp.TextAttachmentPointType.html","topicUid":"ACadSharp.TextAttachmentPointType","type":"Enum"},{"name":"TextAttachmentType","href":"ACadSharp.TextAttachmentType.html","topicHref":"ACadSharp.TextAttachmentType.html","topicUid":"ACadSharp.TextAttachmentType","type":"Enum"},{"name":"Transparency","href":"ACadSharp.Transparency.html","topicHref":"ACadSharp.Transparency.html","topicUid":"ACadSharp.Transparency","type":"Struct"}]},{"name":"ACadSharp.Attributes","href":"ACadSharp.Attributes.html","topicHref":"ACadSharp.Attributes.html","topicUid":"ACadSharp.Attributes","type":"Namespace","items":[{"name":"CadSystemVariableAttribute","href":"ACadSharp.Attributes.CadSystemVariableAttribute.html","topicHref":"ACadSharp.Attributes.CadSystemVariableAttribute.html","topicUid":"ACadSharp.Attributes.CadSystemVariableAttribute","type":"Class"},{"name":"DxfCodeValueAttribute","href":"ACadSharp.Attributes.DxfCodeValueAttribute.html","topicHref":"ACadSharp.Attributes.DxfCodeValueAttribute.html","topicUid":"ACadSharp.Attributes.DxfCodeValueAttribute","type":"Class"},{"name":"DxfCollectionCodeValueAttribute","href":"ACadSharp.Attributes.DxfCollectionCodeValueAttribute.html","topicHref":"ACadSharp.Attributes.DxfCollectionCodeValueAttribute.html","topicUid":"ACadSharp.Attributes.DxfCollectionCodeValueAttribute","type":"Class"},{"name":"DxfNameAttribute","href":"ACadSharp.Attributes.DxfNameAttribute.html","topicHref":"ACadSharp.Attributes.DxfNameAttribute.html","topicUid":"ACadSharp.Attributes.DxfNameAttribute","type":"Class"},{"name":"DxfSubClassAttribute","href":"ACadSharp.Attributes.DxfSubClassAttribute.html","topicHref":"ACadSharp.Attributes.DxfSubClassAttribute.html","topicUid":"ACadSharp.Attributes.DxfSubClassAttribute","type":"Class"},{"name":"ICodeValueAttribute","href":"ACadSharp.Attributes.ICodeValueAttribute.html","topicHref":"ACadSharp.Attributes.ICodeValueAttribute.html","topicUid":"ACadSharp.Attributes.ICodeValueAttribute","type":"Interface"}]},{"name":"ACadSharp.Blocks","href":"ACadSharp.Blocks.html","topicHref":"ACadSharp.Blocks.html","topicUid":"ACadSharp.Blocks","type":"Namespace","items":[{"name":"Block","href":"ACadSharp.Blocks.Block.html","topicHref":"ACadSharp.Blocks.Block.html","topicUid":"ACadSharp.Blocks.Block","type":"Class"},{"name":"BlockEnd","href":"ACadSharp.Blocks.BlockEnd.html","topicHref":"ACadSharp.Blocks.BlockEnd.html","topicUid":"ACadSharp.Blocks.BlockEnd","type":"Class"},{"name":"BlockTypeFlags","href":"ACadSharp.Blocks.BlockTypeFlags.html","topicHref":"ACadSharp.Blocks.BlockTypeFlags.html","topicUid":"ACadSharp.Blocks.BlockTypeFlags","type":"Enum"},{"name":"DimensionArrowhead","href":"ACadSharp.Blocks.DimensionArrowhead.html","topicHref":"ACadSharp.Blocks.DimensionArrowhead.html","topicUid":"ACadSharp.Blocks.DimensionArrowhead","type":"Class"}]},{"name":"ACadSharp.Classes","href":"ACadSharp.Classes.html","topicHref":"ACadSharp.Classes.html","topicUid":"ACadSharp.Classes","type":"Namespace","items":[{"name":"DxfClass","href":"ACadSharp.Classes.DxfClass.html","topicHref":"ACadSharp.Classes.DxfClass.html","topicUid":"ACadSharp.Classes.DxfClass","type":"Class"},{"name":"DxfClassCollection","href":"ACadSharp.Classes.DxfClassCollection.html","topicHref":"ACadSharp.Classes.DxfClassCollection.html","topicUid":"ACadSharp.Classes.DxfClassCollection","type":"Class"},{"name":"ProxyFlags","href":"ACadSharp.Classes.ProxyFlags.html","topicHref":"ACadSharp.Classes.ProxyFlags.html","topicUid":"ACadSharp.Classes.ProxyFlags","type":"Enum"}]},{"name":"ACadSharp.Entities","href":"ACadSharp.Entities.html","topicHref":"ACadSharp.Entities.html","topicUid":"ACadSharp.Entities","type":"Namespace","items":[{"name":"Arc","href":"ACadSharp.Entities.Arc.html","topicHref":"ACadSharp.Entities.Arc.html","topicUid":"ACadSharp.Entities.Arc","type":"Class"},{"name":"AttachmentPointType","href":"ACadSharp.Entities.AttachmentPointType.html","topicHref":"ACadSharp.Entities.AttachmentPointType.html","topicUid":"ACadSharp.Entities.AttachmentPointType","type":"Enum"},{"name":"AttributeBase","href":"ACadSharp.Entities.AttributeBase.html","topicHref":"ACadSharp.Entities.AttributeBase.html","topicUid":"ACadSharp.Entities.AttributeBase","type":"Class"},{"name":"AttributeDefinition","href":"ACadSharp.Entities.AttributeDefinition.html","topicHref":"ACadSharp.Entities.AttributeDefinition.html","topicUid":"ACadSharp.Entities.AttributeDefinition","type":"Class"},{"name":"AttributeEntity","href":"ACadSharp.Entities.AttributeEntity.html","topicHref":"ACadSharp.Entities.AttributeEntity.html","topicUid":"ACadSharp.Entities.AttributeEntity","type":"Class"},{"name":"AttributeFlags","href":"ACadSharp.Entities.AttributeFlags.html","topicHref":"ACadSharp.Entities.AttributeFlags.html","topicUid":"ACadSharp.Entities.AttributeFlags","type":"Enum"},{"name":"AttributeType","href":"ACadSharp.Entities.AttributeType.html","topicHref":"ACadSharp.Entities.AttributeType.html","topicUid":"ACadSharp.Entities.AttributeType","type":"Enum"},{"name":"BackgroundFillFlags","href":"ACadSharp.Entities.BackgroundFillFlags.html","topicHref":"ACadSharp.Entities.BackgroundFillFlags.html","topicUid":"ACadSharp.Entities.BackgroundFillFlags","type":"Enum"},{"name":"BlockContentConnectionType","href":"ACadSharp.Entities.BlockContentConnectionType.html","topicHref":"ACadSharp.Entities.BlockContentConnectionType.html","topicUid":"ACadSharp.Entities.BlockContentConnectionType","type":"Enum"},{"name":"BoundaryPathFlags","href":"ACadSharp.Entities.BoundaryPathFlags.html","topicHref":"ACadSharp.Entities.BoundaryPathFlags.html","topicUid":"ACadSharp.Entities.BoundaryPathFlags","type":"Enum"},{"name":"CadBody","href":"ACadSharp.Entities.CadBody.html","topicHref":"ACadSharp.Entities.CadBody.html","topicUid":"ACadSharp.Entities.CadBody","type":"Class"},{"name":"CadWipeoutBase","href":"ACadSharp.Entities.CadWipeoutBase.html","topicHref":"ACadSharp.Entities.CadWipeoutBase.html","topicUid":"ACadSharp.Entities.CadWipeoutBase","type":"Class"},{"name":"Circle","href":"ACadSharp.Entities.Circle.html","topicHref":"ACadSharp.Entities.Circle.html","topicUid":"ACadSharp.Entities.Circle","type":"Class"},{"name":"ClipMode","href":"ACadSharp.Entities.ClipMode.html","topicHref":"ACadSharp.Entities.ClipMode.html","topicUid":"ACadSharp.Entities.ClipMode","type":"Enum"},{"name":"ClipType","href":"ACadSharp.Entities.ClipType.html","topicHref":"ACadSharp.Entities.ClipType.html","topicUid":"ACadSharp.Entities.ClipType","type":"Enum"},{"name":"ColumnType","href":"ACadSharp.Entities.ColumnType.html","topicHref":"ACadSharp.Entities.ColumnType.html","topicUid":"ACadSharp.Entities.ColumnType","type":"Enum"},{"name":"Dimension","href":"ACadSharp.Entities.Dimension.html","topicHref":"ACadSharp.Entities.Dimension.html","topicUid":"ACadSharp.Entities.Dimension","type":"Class"},{"name":"DimensionAligned","href":"ACadSharp.Entities.DimensionAligned.html","topicHref":"ACadSharp.Entities.DimensionAligned.html","topicUid":"ACadSharp.Entities.DimensionAligned","type":"Class"},{"name":"DimensionAngular2Line","href":"ACadSharp.Entities.DimensionAngular2Line.html","topicHref":"ACadSharp.Entities.DimensionAngular2Line.html","topicUid":"ACadSharp.Entities.DimensionAngular2Line","type":"Class"},{"name":"DimensionAngular3Pt","href":"ACadSharp.Entities.DimensionAngular3Pt.html","topicHref":"ACadSharp.Entities.DimensionAngular3Pt.html","topicUid":"ACadSharp.Entities.DimensionAngular3Pt","type":"Class"},{"name":"DimensionDiameter","href":"ACadSharp.Entities.DimensionDiameter.html","topicHref":"ACadSharp.Entities.DimensionDiameter.html","topicUid":"ACadSharp.Entities.DimensionDiameter","type":"Class"},{"name":"DimensionLinear","href":"ACadSharp.Entities.DimensionLinear.html","topicHref":"ACadSharp.Entities.DimensionLinear.html","topicUid":"ACadSharp.Entities.DimensionLinear","type":"Class"},{"name":"DimensionOrdinate","href":"ACadSharp.Entities.DimensionOrdinate.html","topicHref":"ACadSharp.Entities.DimensionOrdinate.html","topicUid":"ACadSharp.Entities.DimensionOrdinate","type":"Class"},{"name":"DimensionRadius","href":"ACadSharp.Entities.DimensionRadius.html","topicHref":"ACadSharp.Entities.DimensionRadius.html","topicUid":"ACadSharp.Entities.DimensionRadius","type":"Class"},{"name":"DimensionType","href":"ACadSharp.Entities.DimensionType.html","topicHref":"ACadSharp.Entities.DimensionType.html","topicUid":"ACadSharp.Entities.DimensionType","type":"Enum"},{"name":"DrawingDirectionType","href":"ACadSharp.Entities.DrawingDirectionType.html","topicHref":"ACadSharp.Entities.DrawingDirectionType.html","topicUid":"ACadSharp.Entities.DrawingDirectionType","type":"Enum"},{"name":"Ellipse","href":"ACadSharp.Entities.Ellipse.html","topicHref":"ACadSharp.Entities.Ellipse.html","topicUid":"ACadSharp.Entities.Ellipse","type":"Class"},{"name":"Entity","href":"ACadSharp.Entities.Entity.html","topicHref":"ACadSharp.Entities.Entity.html","topicUid":"ACadSharp.Entities.Entity","type":"Class"},{"name":"Face3D","href":"ACadSharp.Entities.Face3D.html","topicHref":"ACadSharp.Entities.Face3D.html","topicUid":"ACadSharp.Entities.Face3D","type":"Class"},{"name":"GradientColor","href":"ACadSharp.Entities.GradientColor.html","topicHref":"ACadSharp.Entities.GradientColor.html","topicUid":"ACadSharp.Entities.GradientColor","type":"Class"},{"name":"Hatch","href":"ACadSharp.Entities.Hatch.html","topicHref":"ACadSharp.Entities.Hatch.html","topicUid":"ACadSharp.Entities.Hatch","type":"Class"},{"name":"Hatch.BoundaryPath","href":"ACadSharp.Entities.Hatch.BoundaryPath.html","topicHref":"ACadSharp.Entities.Hatch.BoundaryPath.html","topicUid":"ACadSharp.Entities.Hatch.BoundaryPath","type":"Class"},{"name":"Hatch.BoundaryPath.Arc","href":"ACadSharp.Entities.Hatch.BoundaryPath.Arc.html","topicHref":"ACadSharp.Entities.Hatch.BoundaryPath.Arc.html","topicUid":"ACadSharp.Entities.Hatch.BoundaryPath.Arc","type":"Class"},{"name":"Hatch.BoundaryPath.Edge","href":"ACadSharp.Entities.Hatch.BoundaryPath.Edge.html","topicHref":"ACadSharp.Entities.Hatch.BoundaryPath.Edge.html","topicUid":"ACadSharp.Entities.Hatch.BoundaryPath.Edge","type":"Class"},{"name":"Hatch.BoundaryPath.EdgeType","href":"ACadSharp.Entities.Hatch.BoundaryPath.EdgeType.html","topicHref":"ACadSharp.Entities.Hatch.BoundaryPath.EdgeType.html","topicUid":"ACadSharp.Entities.Hatch.BoundaryPath.EdgeType","type":"Enum"},{"name":"Hatch.BoundaryPath.Ellipse","href":"ACadSharp.Entities.Hatch.BoundaryPath.Ellipse.html","topicHref":"ACadSharp.Entities.Hatch.BoundaryPath.Ellipse.html","topicUid":"ACadSharp.Entities.Hatch.BoundaryPath.Ellipse","type":"Class"},{"name":"Hatch.BoundaryPath.Line","href":"ACadSharp.Entities.Hatch.BoundaryPath.Line.html","topicHref":"ACadSharp.Entities.Hatch.BoundaryPath.Line.html","topicUid":"ACadSharp.Entities.Hatch.BoundaryPath.Line","type":"Class"},{"name":"Hatch.BoundaryPath.Polyline","href":"ACadSharp.Entities.Hatch.BoundaryPath.Polyline.html","topicHref":"ACadSharp.Entities.Hatch.BoundaryPath.Polyline.html","topicUid":"ACadSharp.Entities.Hatch.BoundaryPath.Polyline","type":"Class"},{"name":"Hatch.BoundaryPath.Spline","href":"ACadSharp.Entities.Hatch.BoundaryPath.Spline.html","topicHref":"ACadSharp.Entities.Hatch.BoundaryPath.Spline.html","topicUid":"ACadSharp.Entities.Hatch.BoundaryPath.Spline","type":"Class"},{"name":"HatchGradientPattern","href":"ACadSharp.Entities.HatchGradientPattern.html","topicHref":"ACadSharp.Entities.HatchGradientPattern.html","topicUid":"ACadSharp.Entities.HatchGradientPattern","type":"Class"},{"name":"HatchPattern","href":"ACadSharp.Entities.HatchPattern.html","topicHref":"ACadSharp.Entities.HatchPattern.html","topicUid":"ACadSharp.Entities.HatchPattern","type":"Class"},{"name":"HatchPattern.Line","href":"ACadSharp.Entities.HatchPattern.Line.html","topicHref":"ACadSharp.Entities.HatchPattern.Line.html","topicUid":"ACadSharp.Entities.HatchPattern.Line","type":"Class"},{"name":"HatchPatternType","href":"ACadSharp.Entities.HatchPatternType.html","topicHref":"ACadSharp.Entities.HatchPatternType.html","topicUid":"ACadSharp.Entities.HatchPatternType","type":"Enum"},{"name":"HatchStyleType","href":"ACadSharp.Entities.HatchStyleType.html","topicHref":"ACadSharp.Entities.HatchStyleType.html","topicUid":"ACadSharp.Entities.HatchStyleType","type":"Enum"},{"name":"HookLineDirection","href":"ACadSharp.Entities.HookLineDirection.html","topicHref":"ACadSharp.Entities.HookLineDirection.html","topicUid":"ACadSharp.Entities.HookLineDirection","type":"Enum"},{"name":"IEntity","href":"ACadSharp.Entities.IEntity.html","topicHref":"ACadSharp.Entities.IEntity.html","topicUid":"ACadSharp.Entities.IEntity","type":"Interface"},{"name":"IGeometricEntity","href":"ACadSharp.Entities.IGeometricEntity.html","topicHref":"ACadSharp.Entities.IGeometricEntity.html","topicUid":"ACadSharp.Entities.IGeometricEntity","type":"Interface"},{"name":"IPolyline","href":"ACadSharp.Entities.IPolyline.html","topicHref":"ACadSharp.Entities.IPolyline.html","topicUid":"ACadSharp.Entities.IPolyline","type":"Interface"},{"name":"IText","href":"ACadSharp.Entities.IText.html","topicHref":"ACadSharp.Entities.IText.html","topicUid":"ACadSharp.Entities.IText","type":"Interface"},{"name":"IVertex","href":"ACadSharp.Entities.IVertex.html","topicHref":"ACadSharp.Entities.IVertex.html","topicUid":"ACadSharp.Entities.IVertex","type":"Interface"},{"name":"ImageDisplayFlags","href":"ACadSharp.Entities.ImageDisplayFlags.html","topicHref":"ACadSharp.Entities.ImageDisplayFlags.html","topicUid":"ACadSharp.Entities.ImageDisplayFlags","type":"Enum"},{"name":"Insert","href":"ACadSharp.Entities.Insert.html","topicHref":"ACadSharp.Entities.Insert.html","topicUid":"ACadSharp.Entities.Insert","type":"Class"},{"name":"InvisibleEdgeFlags","href":"ACadSharp.Entities.InvisibleEdgeFlags.html","topicHref":"ACadSharp.Entities.InvisibleEdgeFlags.html","topicUid":"ACadSharp.Entities.InvisibleEdgeFlags","type":"Enum"},{"name":"KnotParametrization","href":"ACadSharp.Entities.KnotParametrization.html","topicHref":"ACadSharp.Entities.KnotParametrization.html","topicUid":"ACadSharp.Entities.KnotParametrization","type":"Enum"},{"name":"Leader","href":"ACadSharp.Entities.Leader.html","topicHref":"ACadSharp.Entities.Leader.html","topicUid":"ACadSharp.Entities.Leader","type":"Class"},{"name":"LeaderCreationType","href":"ACadSharp.Entities.LeaderCreationType.html","topicHref":"ACadSharp.Entities.LeaderCreationType.html","topicUid":"ACadSharp.Entities.LeaderCreationType","type":"Enum"},{"name":"LeaderPathType","href":"ACadSharp.Entities.LeaderPathType.html","topicHref":"ACadSharp.Entities.LeaderPathType.html","topicUid":"ACadSharp.Entities.LeaderPathType","type":"Enum"},{"name":"LightingType","href":"ACadSharp.Entities.LightingType.html","topicHref":"ACadSharp.Entities.LightingType.html","topicUid":"ACadSharp.Entities.LightingType","type":"Enum"},{"name":"Line","href":"ACadSharp.Entities.Line.html","topicHref":"ACadSharp.Entities.Line.html","topicUid":"ACadSharp.Entities.Line","type":"Class"},{"name":"LineSpacingStyleType","href":"ACadSharp.Entities.LineSpacingStyleType.html","topicHref":"ACadSharp.Entities.LineSpacingStyleType.html","topicUid":"ACadSharp.Entities.LineSpacingStyleType","type":"Enum"},{"name":"LwPolyline","href":"ACadSharp.Entities.LwPolyline.html","topicHref":"ACadSharp.Entities.LwPolyline.html","topicUid":"ACadSharp.Entities.LwPolyline","type":"Class"},{"name":"LwPolyline.Vertex","href":"ACadSharp.Entities.LwPolyline.Vertex.html","topicHref":"ACadSharp.Entities.LwPolyline.Vertex.html","topicUid":"ACadSharp.Entities.LwPolyline.Vertex","type":"Class"},{"name":"LwPolylineFlags","href":"ACadSharp.Entities.LwPolylineFlags.html","topicHref":"ACadSharp.Entities.LwPolylineFlags.html","topicUid":"ACadSharp.Entities.LwPolylineFlags","type":"Enum"},{"name":"MLine","href":"ACadSharp.Entities.MLine.html","topicHref":"ACadSharp.Entities.MLine.html","topicUid":"ACadSharp.Entities.MLine","type":"Class"},{"name":"MLine.Vertex","href":"ACadSharp.Entities.MLine.Vertex.html","topicHref":"ACadSharp.Entities.MLine.Vertex.html","topicUid":"ACadSharp.Entities.MLine.Vertex","type":"Class"},{"name":"MLine.Vertex.Segment","href":"ACadSharp.Entities.MLine.Vertex.Segment.html","topicHref":"ACadSharp.Entities.MLine.Vertex.Segment.html","topicUid":"ACadSharp.Entities.MLine.Vertex.Segment","type":"Class"},{"name":"MLineFlags","href":"ACadSharp.Entities.MLineFlags.html","topicHref":"ACadSharp.Entities.MLineFlags.html","topicUid":"ACadSharp.Entities.MLineFlags","type":"Enum"},{"name":"MLineJustification","href":"ACadSharp.Entities.MLineJustification.html","topicHref":"ACadSharp.Entities.MLineJustification.html","topicUid":"ACadSharp.Entities.MLineJustification","type":"Enum"},{"name":"MText","href":"ACadSharp.Entities.MText.html","topicHref":"ACadSharp.Entities.MText.html","topicUid":"ACadSharp.Entities.MText","type":"Class"},{"name":"MText.TextColumnData","href":"ACadSharp.Entities.MText.TextColumnData.html","topicHref":"ACadSharp.Entities.MText.TextColumnData.html","topicUid":"ACadSharp.Entities.MText.TextColumnData","type":"Class"},{"name":"Mesh","href":"ACadSharp.Entities.Mesh.html","topicHref":"ACadSharp.Entities.Mesh.html","topicUid":"ACadSharp.Entities.Mesh","type":"Class"},{"name":"Mesh.Edge","href":"ACadSharp.Entities.Mesh.Edge.html","topicHref":"ACadSharp.Entities.Mesh.Edge.html","topicUid":"ACadSharp.Entities.Mesh.Edge","type":"Struct"},{"name":"ModelerGeometry","href":"ACadSharp.Entities.ModelerGeometry.html","topicHref":"ACadSharp.Entities.ModelerGeometry.html","topicUid":"ACadSharp.Entities.ModelerGeometry","type":"Class"},{"name":"ModelerGeometry.Silhouette","href":"ACadSharp.Entities.ModelerGeometry.Silhouette.html","topicHref":"ACadSharp.Entities.ModelerGeometry.Silhouette.html","topicUid":"ACadSharp.Entities.ModelerGeometry.Silhouette","type":"Class"},{"name":"ModelerGeometry.Wire","href":"ACadSharp.Entities.ModelerGeometry.Wire.html","topicHref":"ACadSharp.Entities.ModelerGeometry.Wire.html","topicUid":"ACadSharp.Entities.ModelerGeometry.Wire","type":"Class"},{"name":"MultiLeader","href":"ACadSharp.Entities.MultiLeader.html","topicHref":"ACadSharp.Entities.MultiLeader.html","topicUid":"ACadSharp.Entities.MultiLeader","type":"Class"},{"name":"MultiLeader.BlockAttribute","href":"ACadSharp.Entities.MultiLeader.BlockAttribute.html","topicHref":"ACadSharp.Entities.MultiLeader.BlockAttribute.html","topicUid":"ACadSharp.Entities.MultiLeader.BlockAttribute","type":"Class"},{"name":"MultiLeaderPropertyOverrideFlags","href":"ACadSharp.Entities.MultiLeaderPropertyOverrideFlags.html","topicHref":"ACadSharp.Entities.MultiLeaderPropertyOverrideFlags.html","topicUid":"ACadSharp.Entities.MultiLeaderPropertyOverrideFlags","type":"Enum"},{"name":"Ole2Frame","href":"ACadSharp.Entities.Ole2Frame.html","topicHref":"ACadSharp.Entities.Ole2Frame.html","topicUid":"ACadSharp.Entities.Ole2Frame","type":"Class"},{"name":"OleObjectType","href":"ACadSharp.Entities.OleObjectType.html","topicHref":"ACadSharp.Entities.OleObjectType.html","topicUid":"ACadSharp.Entities.OleObjectType","type":"Enum"},{"name":"PdfUnderlay","href":"ACadSharp.Entities.PdfUnderlay.html","topicHref":"ACadSharp.Entities.PdfUnderlay.html","topicUid":"ACadSharp.Entities.PdfUnderlay","type":"Class"},{"name":"Point","href":"ACadSharp.Entities.Point.html","topicHref":"ACadSharp.Entities.Point.html","topicUid":"ACadSharp.Entities.Point","type":"Class"},{"name":"PolyfaceMesh","href":"ACadSharp.Entities.PolyfaceMesh.html","topicHref":"ACadSharp.Entities.PolyfaceMesh.html","topicUid":"ACadSharp.Entities.PolyfaceMesh","type":"Class"},{"name":"PolygonMesh","href":"ACadSharp.Entities.PolygonMesh.html","topicHref":"ACadSharp.Entities.PolygonMesh.html","topicUid":"ACadSharp.Entities.PolygonMesh","type":"Class"},{"name":"PolygonMeshVertex","href":"ACadSharp.Entities.PolygonMeshVertex.html","topicHref":"ACadSharp.Entities.PolygonMeshVertex.html","topicUid":"ACadSharp.Entities.PolygonMeshVertex","type":"Class"},{"name":"Polyline2D","href":"ACadSharp.Entities.Polyline2D.html","topicHref":"ACadSharp.Entities.Polyline2D.html","topicUid":"ACadSharp.Entities.Polyline2D","type":"Class"},{"name":"Polyline3D","href":"ACadSharp.Entities.Polyline3D.html","topicHref":"ACadSharp.Entities.Polyline3D.html","topicUid":"ACadSharp.Entities.Polyline3D","type":"Class"},{"name":"PolylineFlags","href":"ACadSharp.Entities.PolylineFlags.html","topicHref":"ACadSharp.Entities.PolylineFlags.html","topicUid":"ACadSharp.Entities.PolylineFlags","type":"Enum"},{"name":"Polyline<T>","href":"ACadSharp.Entities.Polyline-1.html","topicHref":"ACadSharp.Entities.Polyline-1.html","topicUid":"ACadSharp.Entities.Polyline`1","type":"Class"},{"name":"ProxyEntity","href":"ACadSharp.Entities.ProxyEntity.html","topicHref":"ACadSharp.Entities.ProxyEntity.html","topicUid":"ACadSharp.Entities.ProxyEntity","type":"Class"},{"name":"RasterImage","href":"ACadSharp.Entities.RasterImage.html","topicHref":"ACadSharp.Entities.RasterImage.html","topicUid":"ACadSharp.Entities.RasterImage","type":"Class"},{"name":"Ray","href":"ACadSharp.Entities.Ray.html","topicHref":"ACadSharp.Entities.Ray.html","topicUid":"ACadSharp.Entities.Ray","type":"Class"},{"name":"Region","href":"ACadSharp.Entities.Region.html","topicHref":"ACadSharp.Entities.Region.html","topicUid":"ACadSharp.Entities.Region","type":"Class"},{"name":"Seqend","href":"ACadSharp.Entities.Seqend.html","topicHref":"ACadSharp.Entities.Seqend.html","topicUid":"ACadSharp.Entities.Seqend","type":"Class"},{"name":"ShadowMode","href":"ACadSharp.Entities.ShadowMode.html","topicHref":"ACadSharp.Entities.ShadowMode.html","topicUid":"ACadSharp.Entities.ShadowMode","type":"Enum"},{"name":"Shape","href":"ACadSharp.Entities.Shape.html","topicHref":"ACadSharp.Entities.Shape.html","topicUid":"ACadSharp.Entities.Shape","type":"Class"},{"name":"SmoothSurfaceType","href":"ACadSharp.Entities.SmoothSurfaceType.html","topicHref":"ACadSharp.Entities.SmoothSurfaceType.html","topicUid":"ACadSharp.Entities.SmoothSurfaceType","type":"Enum"},{"name":"Solid","href":"ACadSharp.Entities.Solid.html","topicHref":"ACadSharp.Entities.Solid.html","topicUid":"ACadSharp.Entities.Solid","type":"Class"},{"name":"Solid3D","href":"ACadSharp.Entities.Solid3D.html","topicHref":"ACadSharp.Entities.Solid3D.html","topicUid":"ACadSharp.Entities.Solid3D","type":"Class"},{"name":"Spline","href":"ACadSharp.Entities.Spline.html","topicHref":"ACadSharp.Entities.Spline.html","topicUid":"ACadSharp.Entities.Spline","type":"Class"},{"name":"SplineFlags","href":"ACadSharp.Entities.SplineFlags.html","topicHref":"ACadSharp.Entities.SplineFlags.html","topicUid":"ACadSharp.Entities.SplineFlags","type":"Enum"},{"name":"SplineFlags1","href":"ACadSharp.Entities.SplineFlags1.html","topicHref":"ACadSharp.Entities.SplineFlags1.html","topicUid":"ACadSharp.Entities.SplineFlags1","type":"Enum"},{"name":"TableEntity","href":"ACadSharp.Entities.TableEntity.html","topicHref":"ACadSharp.Entities.TableEntity.html","topicUid":"ACadSharp.Entities.TableEntity","type":"Class"},{"name":"TableEntity.BreakFlowDirection","href":"ACadSharp.Entities.TableEntity.BreakFlowDirection.html","topicHref":"ACadSharp.Entities.TableEntity.BreakFlowDirection.html","topicUid":"ACadSharp.Entities.TableEntity.BreakFlowDirection","type":"Enum"},{"name":"TableEntity.BreakOptionFlags","href":"ACadSharp.Entities.TableEntity.BreakOptionFlags.html","topicHref":"ACadSharp.Entities.TableEntity.BreakOptionFlags.html","topicUid":"ACadSharp.Entities.TableEntity.BreakOptionFlags","type":"Enum"},{"name":"TableEntity.Cell","href":"ACadSharp.Entities.TableEntity.Cell.html","topicHref":"ACadSharp.Entities.TableEntity.Cell.html","topicUid":"ACadSharp.Entities.TableEntity.Cell","type":"Class"},{"name":"TableEntity.CellContent","href":"ACadSharp.Entities.TableEntity.CellContent.html","topicHref":"ACadSharp.Entities.TableEntity.CellContent.html","topicUid":"ACadSharp.Entities.TableEntity.CellContent","type":"Class"},{"name":"TableEntity.CellContentGeometry","href":"ACadSharp.Entities.TableEntity.CellContentGeometry.html","topicHref":"ACadSharp.Entities.TableEntity.CellContentGeometry.html","topicUid":"ACadSharp.Entities.TableEntity.CellContentGeometry","type":"Class"},{"name":"TableEntity.CellRange","href":"ACadSharp.Entities.TableEntity.CellRange.html","topicHref":"ACadSharp.Entities.TableEntity.CellRange.html","topicUid":"ACadSharp.Entities.TableEntity.CellRange","type":"Class"},{"name":"TableEntity.CellType","href":"ACadSharp.Entities.TableEntity.CellType.html","topicHref":"ACadSharp.Entities.TableEntity.CellType.html","topicUid":"ACadSharp.Entities.TableEntity.CellType","type":"Enum"},{"name":"TableEntity.Column","href":"ACadSharp.Entities.TableEntity.Column.html","topicHref":"ACadSharp.Entities.TableEntity.Column.html","topicUid":"ACadSharp.Entities.TableEntity.Column","type":"Class"},{"name":"TableEntity.CustomDataEntry","href":"ACadSharp.Entities.TableEntity.CustomDataEntry.html","topicHref":"ACadSharp.Entities.TableEntity.CustomDataEntry.html","topicUid":"ACadSharp.Entities.TableEntity.CustomDataEntry","type":"Class"},{"name":"TableEntity.ITableComponent","href":"ACadSharp.Entities.TableEntity.ITableComponent.html","topicHref":"ACadSharp.Entities.TableEntity.ITableComponent.html","topicUid":"ACadSharp.Entities.TableEntity.ITableComponent","type":"Interface"},{"name":"TableEntity.Row","href":"ACadSharp.Entities.TableEntity.Row.html","topicHref":"ACadSharp.Entities.TableEntity.Row.html","topicUid":"ACadSharp.Entities.TableEntity.Row","type":"Class"},{"name":"TableEntity.TableAttribute","href":"ACadSharp.Entities.TableEntity.TableAttribute.html","topicHref":"ACadSharp.Entities.TableEntity.TableAttribute.html","topicUid":"ACadSharp.Entities.TableEntity.TableAttribute","type":"Class"},{"name":"TableEntity.TableBreakData","href":"ACadSharp.Entities.TableEntity.TableBreakData.html","topicHref":"ACadSharp.Entities.TableEntity.TableBreakData.html","topicUid":"ACadSharp.Entities.TableEntity.TableBreakData","type":"Class"},{"name":"TableEntity.TableBreakData.BreakHeight","href":"ACadSharp.Entities.TableEntity.TableBreakData.BreakHeight.html","topicHref":"ACadSharp.Entities.TableEntity.TableBreakData.BreakHeight.html","topicUid":"ACadSharp.Entities.TableEntity.TableBreakData.BreakHeight","type":"Struct"},{"name":"TableEntity.TableCellContentType","href":"ACadSharp.Entities.TableEntity.TableCellContentType.html","topicHref":"ACadSharp.Entities.TableEntity.TableCellContentType.html","topicUid":"ACadSharp.Entities.TableEntity.TableCellContentType","type":"Enum"},{"name":"TableEntity.TableCellStateFlags","href":"ACadSharp.Entities.TableEntity.TableCellStateFlags.html","topicHref":"ACadSharp.Entities.TableEntity.TableCellStateFlags.html","topicUid":"ACadSharp.Entities.TableEntity.TableCellStateFlags","type":"Enum"},{"name":"TableEntity.ValueUnitType","href":"ACadSharp.Entities.TableEntity.ValueUnitType.html","topicHref":"ACadSharp.Entities.TableEntity.ValueUnitType.html","topicUid":"ACadSharp.Entities.TableEntity.ValueUnitType","type":"Enum"},{"name":"TextEntity","href":"ACadSharp.Entities.TextEntity.html","topicHref":"ACadSharp.Entities.TextEntity.html","topicUid":"ACadSharp.Entities.TextEntity","type":"Class"},{"name":"TextHorizontalAlignment","href":"ACadSharp.Entities.TextHorizontalAlignment.html","topicHref":"ACadSharp.Entities.TextHorizontalAlignment.html","topicUid":"ACadSharp.Entities.TextHorizontalAlignment","type":"Enum"},{"name":"TextMirrorFlag","href":"ACadSharp.Entities.TextMirrorFlag.html","topicHref":"ACadSharp.Entities.TextMirrorFlag.html","topicUid":"ACadSharp.Entities.TextMirrorFlag","type":"Enum"},{"name":"TextVerticalAlignmentType","href":"ACadSharp.Entities.TextVerticalAlignmentType.html","topicHref":"ACadSharp.Entities.TextVerticalAlignmentType.html","topicUid":"ACadSharp.Entities.TextVerticalAlignmentType","type":"Enum"},{"name":"Tolerance","href":"ACadSharp.Entities.Tolerance.html","topicHref":"ACadSharp.Entities.Tolerance.html","topicUid":"ACadSharp.Entities.Tolerance","type":"Class"},{"name":"UnderlayDisplayFlags","href":"ACadSharp.Entities.UnderlayDisplayFlags.html","topicHref":"ACadSharp.Entities.UnderlayDisplayFlags.html","topicUid":"ACadSharp.Entities.UnderlayDisplayFlags","type":"Enum"},{"name":"UnderlayEntity<T>","href":"ACadSharp.Entities.UnderlayEntity-1.html","topicHref":"ACadSharp.Entities.UnderlayEntity-1.html","topicUid":"ACadSharp.Entities.UnderlayEntity`1","type":"Class"},{"name":"UnknownEntity","href":"ACadSharp.Entities.UnknownEntity.html","topicHref":"ACadSharp.Entities.UnknownEntity.html","topicUid":"ACadSharp.Entities.UnknownEntity","type":"Class"},{"name":"Vertex","href":"ACadSharp.Entities.Vertex.html","topicHref":"ACadSharp.Entities.Vertex.html","topicUid":"ACadSharp.Entities.Vertex","type":"Class"},{"name":"Vertex2D","href":"ACadSharp.Entities.Vertex2D.html","topicHref":"ACadSharp.Entities.Vertex2D.html","topicUid":"ACadSharp.Entities.Vertex2D","type":"Class"},{"name":"Vertex3D","href":"ACadSharp.Entities.Vertex3D.html","topicHref":"ACadSharp.Entities.Vertex3D.html","topicUid":"ACadSharp.Entities.Vertex3D","type":"Class"},{"name":"VertexFaceMesh","href":"ACadSharp.Entities.VertexFaceMesh.html","topicHref":"ACadSharp.Entities.VertexFaceMesh.html","topicUid":"ACadSharp.Entities.VertexFaceMesh","type":"Class"},{"name":"VertexFaceRecord","href":"ACadSharp.Entities.VertexFaceRecord.html","topicHref":"ACadSharp.Entities.VertexFaceRecord.html","topicUid":"ACadSharp.Entities.VertexFaceRecord","type":"Class"},{"name":"VertexFlags","href":"ACadSharp.Entities.VertexFlags.html","topicHref":"ACadSharp.Entities.VertexFlags.html","topicUid":"ACadSharp.Entities.VertexFlags","type":"Enum"},{"name":"VerticalAlignmentType","href":"ACadSharp.Entities.VerticalAlignmentType.html","topicHref":"ACadSharp.Entities.VerticalAlignmentType.html","topicUid":"ACadSharp.Entities.VerticalAlignmentType","type":"Enum"},{"name":"Viewport","href":"ACadSharp.Entities.Viewport.html","topicHref":"ACadSharp.Entities.Viewport.html","topicUid":"ACadSharp.Entities.Viewport","type":"Class"},{"name":"ViewportStatusFlags","href":"ACadSharp.Entities.ViewportStatusFlags.html","topicHref":"ACadSharp.Entities.ViewportStatusFlags.html","topicUid":"ACadSharp.Entities.ViewportStatusFlags","type":"Enum"},{"name":"Wipeout","href":"ACadSharp.Entities.Wipeout.html","topicHref":"ACadSharp.Entities.Wipeout.html","topicUid":"ACadSharp.Entities.Wipeout","type":"Class"},{"name":"XLine","href":"ACadSharp.Entities.XLine.html","topicHref":"ACadSharp.Entities.XLine.html","topicUid":"ACadSharp.Entities.XLine","type":"Class"}]},{"name":"ACadSharp.Entities.AecObjects","href":"ACadSharp.Entities.AecObjects.html","topicHref":"ACadSharp.Entities.AecObjects.html","topicUid":"ACadSharp.Entities.AecObjects","type":"Namespace","items":[{"name":"Wall","href":"ACadSharp.Entities.AecObjects.Wall.html","topicHref":"ACadSharp.Entities.AecObjects.Wall.html","topicUid":"ACadSharp.Entities.AecObjects.Wall","type":"Class"}]},{"name":"ACadSharp.Exceptions","href":"ACadSharp.Exceptions.html","topicHref":"ACadSharp.Exceptions.html","topicUid":"ACadSharp.Exceptions","type":"Namespace","items":[{"name":"CadNotSupportedException","href":"ACadSharp.Exceptions.CadNotSupportedException.html","topicHref":"ACadSharp.Exceptions.CadNotSupportedException.html","topicUid":"ACadSharp.Exceptions.CadNotSupportedException","type":"Class"},{"name":"DwgException","href":"ACadSharp.Exceptions.DwgException.html","topicHref":"ACadSharp.Exceptions.DwgException.html","topicUid":"ACadSharp.Exceptions.DwgException","type":"Class"},{"name":"DxfException","href":"ACadSharp.Exceptions.DxfException.html","topicHref":"ACadSharp.Exceptions.DxfException.html","topicUid":"ACadSharp.Exceptions.DxfException","type":"Class"}]},{"name":"ACadSharp.Extensions","href":"ACadSharp.Extensions.html","topicHref":"ACadSharp.Extensions.html","topicUid":"ACadSharp.Extensions","type":"Namespace","items":[{"name":"CadObjectExtensions","href":"ACadSharp.Extensions.CadObjectExtensions.html","topicHref":"ACadSharp.Extensions.CadObjectExtensions.html","topicUid":"ACadSharp.Extensions.CadObjectExtensions","type":"Class"},{"name":"INamedCadObjectExtensions","href":"ACadSharp.Extensions.INamedCadObjectExtensions.html","topicHref":"ACadSharp.Extensions.INamedCadObjectExtensions.html","topicUid":"ACadSharp.Extensions.INamedCadObjectExtensions","type":"Class"},{"name":"LineWeightTypeExtensions","href":"ACadSharp.Extensions.LineWeightTypeExtensions.html","topicHref":"ACadSharp.Extensions.LineWeightTypeExtensions.html","topicUid":"ACadSharp.Extensions.LineWeightTypeExtensions","type":"Class"},{"name":"PolylineExtensions","href":"ACadSharp.Extensions.PolylineExtensions.html","topicHref":"ACadSharp.Extensions.PolylineExtensions.html","topicUid":"ACadSharp.Extensions.PolylineExtensions","type":"Class"},{"name":"UnitExtensions","href":"ACadSharp.Extensions.UnitExtensions.html","topicHref":"ACadSharp.Extensions.UnitExtensions.html","topicUid":"ACadSharp.Extensions.UnitExtensions","type":"Class"}]},{"name":"ACadSharp.Header","href":"ACadSharp.Header.html","topicHref":"ACadSharp.Header.html","topicUid":"ACadSharp.Header","type":"Namespace","items":[{"name":"AttributeVisibilityMode","href":"ACadSharp.Header.AttributeVisibilityMode.html","topicHref":"ACadSharp.Header.AttributeVisibilityMode.html","topicUid":"ACadSharp.Header.AttributeVisibilityMode","type":"Enum"},{"name":"CadHeader","href":"ACadSharp.Header.CadHeader.html","topicHref":"ACadSharp.Header.CadHeader.html","topicUid":"ACadSharp.Header.CadHeader","type":"Class"},{"name":"DimensionAssociation","href":"ACadSharp.Header.DimensionAssociation.html","topicHref":"ACadSharp.Header.DimensionAssociation.html","topicUid":"ACadSharp.Header.DimensionAssociation","type":"Enum"},{"name":"EntityPlotStyleType","href":"ACadSharp.Header.EntityPlotStyleType.html","topicHref":"ACadSharp.Header.EntityPlotStyleType.html","topicUid":"ACadSharp.Header.EntityPlotStyleType","type":"Enum"},{"name":"IndexCreationFlags","href":"ACadSharp.Header.IndexCreationFlags.html","topicHref":"ACadSharp.Header.IndexCreationFlags.html","topicUid":"ACadSharp.Header.IndexCreationFlags","type":"Enum"},{"name":"MeasurementUnits","href":"ACadSharp.Header.MeasurementUnits.html","topicHref":"ACadSharp.Header.MeasurementUnits.html","topicUid":"ACadSharp.Header.MeasurementUnits","type":"Enum"},{"name":"ObjectSnapMode","href":"ACadSharp.Header.ObjectSnapMode.html","topicHref":"ACadSharp.Header.ObjectSnapMode.html","topicUid":"ACadSharp.Header.ObjectSnapMode","type":"Enum"},{"name":"ObjectSortingFlags","href":"ACadSharp.Header.ObjectSortingFlags.html","topicHref":"ACadSharp.Header.ObjectSortingFlags.html","topicUid":"ACadSharp.Header.ObjectSortingFlags","type":"Enum"},{"name":"ShadeEdgeType","href":"ACadSharp.Header.ShadeEdgeType.html","topicHref":"ACadSharp.Header.ShadeEdgeType.html","topicUid":"ACadSharp.Header.ShadeEdgeType","type":"Enum"},{"name":"ShadowMode","href":"ACadSharp.Header.ShadowMode.html","topicHref":"ACadSharp.Header.ShadowMode.html","topicUid":"ACadSharp.Header.ShadowMode","type":"Enum"},{"name":"SpaceLineTypeScaling","href":"ACadSharp.Header.SpaceLineTypeScaling.html","topicHref":"ACadSharp.Header.SpaceLineTypeScaling.html","topicUid":"ACadSharp.Header.SpaceLineTypeScaling","type":"Enum"},{"name":"SplineType","href":"ACadSharp.Header.SplineType.html","topicHref":"ACadSharp.Header.SplineType.html","topicUid":"ACadSharp.Header.SplineType","type":"Enum"},{"name":"XClipFrameType","href":"ACadSharp.Header.XClipFrameType.html","topicHref":"ACadSharp.Header.XClipFrameType.html","topicUid":"ACadSharp.Header.XClipFrameType","type":"Enum"}]},{"name":"ACadSharp.IO","href":"ACadSharp.IO.html","topicHref":"ACadSharp.IO.html","topicUid":"ACadSharp.IO","type":"Namespace","items":[{"name":"CadFileFormat","href":"ACadSharp.IO.CadFileFormat.html","topicHref":"ACadSharp.IO.CadFileFormat.html","topicUid":"ACadSharp.IO.CadFileFormat","type":"Enum"},{"name":"CadObjectData","href":"ACadSharp.IO.CadObjectData.html","topicHref":"ACadSharp.IO.CadObjectData.html","topicUid":"ACadSharp.IO.CadObjectData","type":"Struct"},{"name":"CadReaderBase<T>","href":"ACadSharp.IO.CadReaderBase-1.html","topicHref":"ACadSharp.IO.CadReaderBase-1.html","topicUid":"ACadSharp.IO.CadReaderBase`1","type":"Class"},{"name":"CadReaderConfiguration","href":"ACadSharp.IO.CadReaderConfiguration.html","topicHref":"ACadSharp.IO.CadReaderConfiguration.html","topicUid":"ACadSharp.IO.CadReaderConfiguration","type":"Class"},{"name":"CadReaderFactory","href":"ACadSharp.IO.CadReaderFactory.html","topicHref":"ACadSharp.IO.CadReaderFactory.html","topicUid":"ACadSharp.IO.CadReaderFactory","type":"Class"},{"name":"CadWriterBase<T>","href":"ACadSharp.IO.CadWriterBase-1.html","topicHref":"ACadSharp.IO.CadWriterBase-1.html","topicUid":"ACadSharp.IO.CadWriterBase`1","type":"Class"},{"name":"CadWriterConfiguration","href":"ACadSharp.IO.CadWriterConfiguration.html","topicHref":"ACadSharp.IO.CadWriterConfiguration.html","topicUid":"ACadSharp.IO.CadWriterConfiguration","type":"Class"},{"name":"DwgReader","href":"ACadSharp.IO.DwgReader.html","topicHref":"ACadSharp.IO.DwgReader.html","topicUid":"ACadSharp.IO.DwgReader","type":"Class"},{"name":"DwgReaderConfiguration","href":"ACadSharp.IO.DwgReaderConfiguration.html","topicHref":"ACadSharp.IO.DwgReaderConfiguration.html","topicUid":"ACadSharp.IO.DwgReaderConfiguration","type":"Class"},{"name":"DwgWriter","href":"ACadSharp.IO.DwgWriter.html","topicHref":"ACadSharp.IO.DwgWriter.html","topicUid":"ACadSharp.IO.DwgWriter","type":"Class"},{"name":"DwgWriterConfiguration","href":"ACadSharp.IO.DwgWriterConfiguration.html","topicHref":"ACadSharp.IO.DwgWriterConfiguration.html","topicUid":"ACadSharp.IO.DwgWriterConfiguration","type":"Class"},{"name":"DxfReader","href":"ACadSharp.IO.DxfReader.html","topicHref":"ACadSharp.IO.DxfReader.html","topicUid":"ACadSharp.IO.DxfReader","type":"Class"},{"name":"DxfReaderConfiguration","href":"ACadSharp.IO.DxfReaderConfiguration.html","topicHref":"ACadSharp.IO.DxfReaderConfiguration.html","topicUid":"ACadSharp.IO.DxfReaderConfiguration","type":"Class"},{"name":"DxfWriter","href":"ACadSharp.IO.DxfWriter.html","topicHref":"ACadSharp.IO.DxfWriter.html","topicUid":"ACadSharp.IO.DxfWriter","type":"Class"},{"name":"DxfWriterConfiguration","href":"ACadSharp.IO.DxfWriterConfiguration.html","topicHref":"ACadSharp.IO.DxfWriterConfiguration.html","topicUid":"ACadSharp.IO.DxfWriterConfiguration","type":"Class"},{"name":"EntityData","href":"ACadSharp.IO.EntityData.html","topicHref":"ACadSharp.IO.EntityData.html","topicUid":"ACadSharp.IO.EntityData","type":"Struct"},{"name":"ICadReader","href":"ACadSharp.IO.ICadReader.html","topicHref":"ACadSharp.IO.ICadReader.html","topicUid":"ACadSharp.IO.ICadReader","type":"Interface"},{"name":"ICadWriter","href":"ACadSharp.IO.ICadWriter.html","topicHref":"ACadSharp.IO.ICadWriter.html","topicUid":"ACadSharp.IO.ICadWriter","type":"Interface"},{"name":"NotificationEventArgs","href":"ACadSharp.IO.NotificationEventArgs.html","topicHref":"ACadSharp.IO.NotificationEventArgs.html","topicUid":"ACadSharp.IO.NotificationEventArgs","type":"Class"},{"name":"NotificationEventHandler","href":"ACadSharp.IO.NotificationEventHandler.html","topicHref":"ACadSharp.IO.NotificationEventHandler.html","topicUid":"ACadSharp.IO.NotificationEventHandler","type":"Delegate"},{"name":"NotificationType","href":"ACadSharp.IO.NotificationType.html","topicHref":"ACadSharp.IO.NotificationType.html","topicUid":"ACadSharp.IO.NotificationType","type":"Enum"},{"name":"ProgressEventArgs","href":"ACadSharp.IO.ProgressEventArgs.html","topicHref":"ACadSharp.IO.ProgressEventArgs.html","topicUid":"ACadSharp.IO.ProgressEventArgs","type":"Class"},{"name":"ProgressEventHandler","href":"ACadSharp.IO.ProgressEventHandler.html","topicHref":"ACadSharp.IO.ProgressEventHandler.html","topicUid":"ACadSharp.IO.ProgressEventHandler","type":"Delegate"},{"name":"ReadStage","href":"ACadSharp.IO.ReadStage.html","topicHref":"ACadSharp.IO.ReadStage.html","topicUid":"ACadSharp.IO.ReadStage","type":"Enum"},{"name":"ReferenceData","href":"ACadSharp.IO.ReferenceData.html","topicHref":"ACadSharp.IO.ReferenceData.html","topicUid":"ACadSharp.IO.ReferenceData","type":"Struct"},{"name":"SvgConfiguration","href":"ACadSharp.IO.SvgConfiguration.html","topicHref":"ACadSharp.IO.SvgConfiguration.html","topicUid":"ACadSharp.IO.SvgConfiguration","type":"Class"},{"name":"SvgWriter","href":"ACadSharp.IO.SvgWriter.html","topicHref":"ACadSharp.IO.SvgWriter.html","topicUid":"ACadSharp.IO.SvgWriter","type":"Class"}]},{"name":"ACadSharp.Objects","href":"ACadSharp.Objects.html","topicHref":"ACadSharp.Objects.html","topicUid":"ACadSharp.Objects","type":"Namespace","items":[{"name":"AcdbPlaceHolder","href":"ACadSharp.Objects.AcdbPlaceHolder.html","topicHref":"ACadSharp.Objects.AcdbPlaceHolder.html","topicUid":"ACadSharp.Objects.AcdbPlaceHolder","type":"Class"},{"name":"AecCleanupGroup","href":"ACadSharp.Objects.AecCleanupGroup.html","topicHref":"ACadSharp.Objects.AecCleanupGroup.html","topicUid":"ACadSharp.Objects.AecCleanupGroup","type":"Class"},{"name":"AecWallStyle","href":"ACadSharp.Objects.AecWallStyle.html","topicHref":"ACadSharp.Objects.AecWallStyle.html","topicUid":"ACadSharp.Objects.AecWallStyle","type":"Class"},{"name":"AnnotScaleObjectContextData","href":"ACadSharp.Objects.AnnotScaleObjectContextData.html","topicHref":"ACadSharp.Objects.AnnotScaleObjectContextData.html","topicUid":"ACadSharp.Objects.AnnotScaleObjectContextData","type":"Class"},{"name":"AssociativityFlags","href":"ACadSharp.Objects.AssociativityFlags.html","topicHref":"ACadSharp.Objects.AssociativityFlags.html","topicUid":"ACadSharp.Objects.AssociativityFlags","type":"Enum"},{"name":"AutoTransformMethodFlags","href":"ACadSharp.Objects.AutoTransformMethodFlags.html","topicHref":"ACadSharp.Objects.AutoTransformMethodFlags.html","topicUid":"ACadSharp.Objects.AutoTransformMethodFlags","type":"Enum"},{"name":"BlockReferenceObjectContextData","href":"ACadSharp.Objects.BlockReferenceObjectContextData.html","topicHref":"ACadSharp.Objects.BlockReferenceObjectContextData.html","topicUid":"ACadSharp.Objects.BlockReferenceObjectContextData","type":"Class"},{"name":"BlockRepresentationData","href":"ACadSharp.Objects.BlockRepresentationData.html","topicHref":"ACadSharp.Objects.BlockRepresentationData.html","topicUid":"ACadSharp.Objects.BlockRepresentationData","type":"Class"},{"name":"BookColor","href":"ACadSharp.Objects.BookColor.html","topicHref":"ACadSharp.Objects.BookColor.html","topicUid":"ACadSharp.Objects.BookColor","type":"Class"},{"name":"CadDictionary","href":"ACadSharp.Objects.CadDictionary.html","topicHref":"ACadSharp.Objects.CadDictionary.html","topicUid":"ACadSharp.Objects.CadDictionary","type":"Class"},{"name":"CadDictionaryWithDefault","href":"ACadSharp.Objects.CadDictionaryWithDefault.html","topicHref":"ACadSharp.Objects.CadDictionaryWithDefault.html","topicUid":"ACadSharp.Objects.CadDictionaryWithDefault","type":"Class"},{"name":"ColorMethod","href":"ACadSharp.Objects.ColorMethod.html","topicHref":"ACadSharp.Objects.ColorMethod.html","topicUid":"ACadSharp.Objects.ColorMethod","type":"Enum"},{"name":"DesignCoordinatesType","href":"ACadSharp.Objects.DesignCoordinatesType.html","topicHref":"ACadSharp.Objects.DesignCoordinatesType.html","topicUid":"ACadSharp.Objects.DesignCoordinatesType","type":"Enum"},{"name":"DictionaryCloningFlags","href":"ACadSharp.Objects.DictionaryCloningFlags.html","topicHref":"ACadSharp.Objects.DictionaryCloningFlags.html","topicUid":"ACadSharp.Objects.DictionaryCloningFlags","type":"Enum"},{"name":"DictionaryVariable","href":"ACadSharp.Objects.DictionaryVariable.html","topicHref":"ACadSharp.Objects.DictionaryVariable.html","topicUid":"ACadSharp.Objects.DictionaryVariable","type":"Class"},{"name":"DimensionAssociation","href":"ACadSharp.Objects.DimensionAssociation.html","topicHref":"ACadSharp.Objects.DimensionAssociation.html","topicUid":"ACadSharp.Objects.DimensionAssociation","type":"Class"},{"name":"DimensionAssociation.OsnapPointRef","href":"ACadSharp.Objects.DimensionAssociation.OsnapPointRef.html","topicHref":"ACadSharp.Objects.DimensionAssociation.OsnapPointRef.html","topicUid":"ACadSharp.Objects.DimensionAssociation.OsnapPointRef","type":"Class"},{"name":"EdgeStyleModel","href":"ACadSharp.Objects.EdgeStyleModel.html","topicHref":"ACadSharp.Objects.EdgeStyleModel.html","topicUid":"ACadSharp.Objects.EdgeStyleModel","type":"Enum"},{"name":"EvaluationOptionFlags","href":"ACadSharp.Objects.EvaluationOptionFlags.html","topicHref":"ACadSharp.Objects.EvaluationOptionFlags.html","topicUid":"ACadSharp.Objects.EvaluationOptionFlags","type":"Enum"},{"name":"EvaluationStatusFlags","href":"ACadSharp.Objects.EvaluationStatusFlags.html","topicHref":"ACadSharp.Objects.EvaluationStatusFlags.html","topicUid":"ACadSharp.Objects.EvaluationStatusFlags","type":"Enum"},{"name":"FaceColorMode","href":"ACadSharp.Objects.FaceColorMode.html","topicHref":"ACadSharp.Objects.FaceColorMode.html","topicUid":"ACadSharp.Objects.FaceColorMode","type":"Enum"},{"name":"FaceLightingModelType","href":"ACadSharp.Objects.FaceLightingModelType.html","topicHref":"ACadSharp.Objects.FaceLightingModelType.html","topicUid":"ACadSharp.Objects.FaceLightingModelType","type":"Enum"},{"name":"FaceLightingQualityType","href":"ACadSharp.Objects.FaceLightingQualityType.html","topicHref":"ACadSharp.Objects.FaceLightingQualityType.html","topicUid":"ACadSharp.Objects.FaceLightingQualityType","type":"Enum"},{"name":"FaceModifierType","href":"ACadSharp.Objects.FaceModifierType.html","topicHref":"ACadSharp.Objects.FaceModifierType.html","topicUid":"ACadSharp.Objects.FaceModifierType","type":"Enum"},{"name":"Field","href":"ACadSharp.Objects.Field.html","topicHref":"ACadSharp.Objects.Field.html","topicUid":"ACadSharp.Objects.Field","type":"Class"},{"name":"FieldList","href":"ACadSharp.Objects.FieldList.html","topicHref":"ACadSharp.Objects.FieldList.html","topicUid":"ACadSharp.Objects.FieldList","type":"Class"},{"name":"FieldStateFlags","href":"ACadSharp.Objects.FieldStateFlags.html","topicHref":"ACadSharp.Objects.FieldStateFlags.html","topicUid":"ACadSharp.Objects.FieldStateFlags","type":"Enum"},{"name":"FilingOptionFlags","href":"ACadSharp.Objects.FilingOptionFlags.html","topicHref":"ACadSharp.Objects.FilingOptionFlags.html","topicUid":"ACadSharp.Objects.FilingOptionFlags","type":"Enum"},{"name":"Filter","href":"ACadSharp.Objects.Filter.html","topicHref":"ACadSharp.Objects.Filter.html","topicUid":"ACadSharp.Objects.Filter","type":"Class"},{"name":"FormattedTableData","href":"ACadSharp.Objects.FormattedTableData.html","topicHref":"ACadSharp.Objects.FormattedTableData.html","topicUid":"ACadSharp.Objects.FormattedTableData","type":"Class"},{"name":"GeoData","href":"ACadSharp.Objects.GeoData.html","topicHref":"ACadSharp.Objects.GeoData.html","topicUid":"ACadSharp.Objects.GeoData","type":"Class"},{"name":"GeoData.GeoMeshFace","href":"ACadSharp.Objects.GeoData.GeoMeshFace.html","topicHref":"ACadSharp.Objects.GeoData.GeoMeshFace.html","topicUid":"ACadSharp.Objects.GeoData.GeoMeshFace","type":"Class"},{"name":"GeoData.GeoMeshPoint","href":"ACadSharp.Objects.GeoData.GeoMeshPoint.html","topicHref":"ACadSharp.Objects.GeoData.GeoMeshPoint.html","topicUid":"ACadSharp.Objects.GeoData.GeoMeshPoint","type":"Class"},{"name":"GeoDataVersion","href":"ACadSharp.Objects.GeoDataVersion.html","topicHref":"ACadSharp.Objects.GeoDataVersion.html","topicUid":"ACadSharp.Objects.GeoDataVersion","type":"Enum"},{"name":"Group","href":"ACadSharp.Objects.Group.html","topicHref":"ACadSharp.Objects.Group.html","topicUid":"ACadSharp.Objects.Group","type":"Class"},{"name":"ImageDefinition","href":"ACadSharp.Objects.ImageDefinition.html","topicHref":"ACadSharp.Objects.ImageDefinition.html","topicUid":"ACadSharp.Objects.ImageDefinition","type":"Class"},{"name":"ImageDefinitionReactor","href":"ACadSharp.Objects.ImageDefinitionReactor.html","topicHref":"ACadSharp.Objects.ImageDefinitionReactor.html","topicUid":"ACadSharp.Objects.ImageDefinitionReactor","type":"Class"},{"name":"ImageDisplayQuality","href":"ACadSharp.Objects.ImageDisplayQuality.html","topicHref":"ACadSharp.Objects.ImageDisplayQuality.html","topicUid":"ACadSharp.Objects.ImageDisplayQuality","type":"Enum"},{"name":"Layout","href":"ACadSharp.Objects.Layout.html","topicHref":"ACadSharp.Objects.Layout.html","topicUid":"ACadSharp.Objects.Layout","type":"Class"},{"name":"LayoutFlags","href":"ACadSharp.Objects.LayoutFlags.html","topicHref":"ACadSharp.Objects.LayoutFlags.html","topicUid":"ACadSharp.Objects.LayoutFlags","type":"Enum"},{"name":"LeaderContentType","href":"ACadSharp.Objects.LeaderContentType.html","topicHref":"ACadSharp.Objects.LeaderContentType.html","topicUid":"ACadSharp.Objects.LeaderContentType","type":"Enum"},{"name":"LeaderDrawOrderType","href":"ACadSharp.Objects.LeaderDrawOrderType.html","topicHref":"ACadSharp.Objects.LeaderDrawOrderType.html","topicUid":"ACadSharp.Objects.LeaderDrawOrderType","type":"Enum"},{"name":"LeaderLinePropertOverrideFlags","href":"ACadSharp.Objects.LeaderLinePropertOverrideFlags.html","topicHref":"ACadSharp.Objects.LeaderLinePropertOverrideFlags.html","topicUid":"ACadSharp.Objects.LeaderLinePropertOverrideFlags","type":"Enum"},{"name":"LinkedData","href":"ACadSharp.Objects.LinkedData.html","topicHref":"ACadSharp.Objects.LinkedData.html","topicUid":"ACadSharp.Objects.LinkedData","type":"Class"},{"name":"LinkedTableData","href":"ACadSharp.Objects.LinkedTableData.html","topicHref":"ACadSharp.Objects.LinkedTableData.html","topicUid":"ACadSharp.Objects.LinkedTableData","type":"Class"},{"name":"MLineStyle","href":"ACadSharp.Objects.MLineStyle.html","topicHref":"ACadSharp.Objects.MLineStyle.html","topicUid":"ACadSharp.Objects.MLineStyle","type":"Class"},{"name":"MLineStyle.Element","href":"ACadSharp.Objects.MLineStyle.Element.html","topicHref":"ACadSharp.Objects.MLineStyle.Element.html","topicUid":"ACadSharp.Objects.MLineStyle.Element","type":"Class"},{"name":"MLineStyleFlags","href":"ACadSharp.Objects.MLineStyleFlags.html","topicHref":"ACadSharp.Objects.MLineStyleFlags.html","topicUid":"ACadSharp.Objects.MLineStyleFlags","type":"Enum"},{"name":"MTextAttributeObjectContextData","href":"ACadSharp.Objects.MTextAttributeObjectContextData.html","topicHref":"ACadSharp.Objects.MTextAttributeObjectContextData.html","topicUid":"ACadSharp.Objects.MTextAttributeObjectContextData","type":"Class"},{"name":"MapSource","href":"ACadSharp.Objects.MapSource.html","topicHref":"ACadSharp.Objects.MapSource.html","topicUid":"ACadSharp.Objects.MapSource","type":"Enum"},{"name":"Material","href":"ACadSharp.Objects.Material.html","topicHref":"ACadSharp.Objects.Material.html","topicUid":"ACadSharp.Objects.Material","type":"Class"},{"name":"MultiLeaderDrawOrderType","href":"ACadSharp.Objects.MultiLeaderDrawOrderType.html","topicHref":"ACadSharp.Objects.MultiLeaderDrawOrderType.html","topicUid":"ACadSharp.Objects.MultiLeaderDrawOrderType","type":"Enum"},{"name":"MultiLeaderObjectContextData","href":"ACadSharp.Objects.MultiLeaderObjectContextData.html","topicHref":"ACadSharp.Objects.MultiLeaderObjectContextData.html","topicUid":"ACadSharp.Objects.MultiLeaderObjectContextData","type":"Class"},{"name":"MultiLeaderObjectContextData.LeaderLine","href":"ACadSharp.Objects.MultiLeaderObjectContextData.LeaderLine.html","topicHref":"ACadSharp.Objects.MultiLeaderObjectContextData.LeaderLine.html","topicUid":"ACadSharp.Objects.MultiLeaderObjectContextData.LeaderLine","type":"Class"},{"name":"MultiLeaderObjectContextData.LeaderRoot","href":"ACadSharp.Objects.MultiLeaderObjectContextData.LeaderRoot.html","topicHref":"ACadSharp.Objects.MultiLeaderObjectContextData.LeaderRoot.html","topicUid":"ACadSharp.Objects.MultiLeaderObjectContextData.LeaderRoot","type":"Class"},{"name":"MultiLeaderObjectContextData.StartEndPointPair","href":"ACadSharp.Objects.MultiLeaderObjectContextData.StartEndPointPair.html","topicHref":"ACadSharp.Objects.MultiLeaderObjectContextData.StartEndPointPair.html","topicUid":"ACadSharp.Objects.MultiLeaderObjectContextData.StartEndPointPair","type":"Struct"},{"name":"MultiLeaderStyle","href":"ACadSharp.Objects.MultiLeaderStyle.html","topicHref":"ACadSharp.Objects.MultiLeaderStyle.html","topicUid":"ACadSharp.Objects.MultiLeaderStyle","type":"Class"},{"name":"NonGraphicalObject","href":"ACadSharp.Objects.NonGraphicalObject.html","topicHref":"ACadSharp.Objects.NonGraphicalObject.html","topicUid":"ACadSharp.Objects.NonGraphicalObject","type":"Class"},{"name":"ObjectContextData","href":"ACadSharp.Objects.ObjectContextData.html","topicHref":"ACadSharp.Objects.ObjectContextData.html","topicUid":"ACadSharp.Objects.ObjectContextData","type":"Class"},{"name":"ObjectOsnapType","href":"ACadSharp.Objects.ObjectOsnapType.html","topicHref":"ACadSharp.Objects.ObjectOsnapType.html","topicUid":"ACadSharp.Objects.ObjectOsnapType","type":"Enum"},{"name":"PaperMargin","href":"ACadSharp.Objects.PaperMargin.html","topicHref":"ACadSharp.Objects.PaperMargin.html","topicUid":"ACadSharp.Objects.PaperMargin","type":"Struct"},{"name":"PdfUnderlayDefinition","href":"ACadSharp.Objects.PdfUnderlayDefinition.html","topicHref":"ACadSharp.Objects.PdfUnderlayDefinition.html","topicUid":"ACadSharp.Objects.PdfUnderlayDefinition","type":"Class"},{"name":"PlotFlags","href":"ACadSharp.Objects.PlotFlags.html","topicHref":"ACadSharp.Objects.PlotFlags.html","topicUid":"ACadSharp.Objects.PlotFlags","type":"Enum"},{"name":"PlotPaperUnits","href":"ACadSharp.Objects.PlotPaperUnits.html","topicHref":"ACadSharp.Objects.PlotPaperUnits.html","topicUid":"ACadSharp.Objects.PlotPaperUnits","type":"Enum"},{"name":"PlotRotation","href":"ACadSharp.Objects.PlotRotation.html","topicHref":"ACadSharp.Objects.PlotRotation.html","topicUid":"ACadSharp.Objects.PlotRotation","type":"Enum"},{"name":"PlotSettings","href":"ACadSharp.Objects.PlotSettings.html","topicHref":"ACadSharp.Objects.PlotSettings.html","topicUid":"ACadSharp.Objects.PlotSettings","type":"Class"},{"name":"PlotType","href":"ACadSharp.Objects.PlotType.html","topicHref":"ACadSharp.Objects.PlotType.html","topicUid":"ACadSharp.Objects.PlotType","type":"Enum"},{"name":"ProjectionMethod","href":"ACadSharp.Objects.ProjectionMethod.html","topicHref":"ACadSharp.Objects.ProjectionMethod.html","topicUid":"ACadSharp.Objects.ProjectionMethod","type":"Enum"},{"name":"ProxyObject","href":"ACadSharp.Objects.ProxyObject.html","topicHref":"ACadSharp.Objects.ProxyObject.html","topicUid":"ACadSharp.Objects.ProxyObject","type":"Class"},{"name":"RasterVariables","href":"ACadSharp.Objects.RasterVariables.html","topicHref":"ACadSharp.Objects.RasterVariables.html","topicUid":"ACadSharp.Objects.RasterVariables","type":"Class"},{"name":"ResolutionUnit","href":"ACadSharp.Objects.ResolutionUnit.html","topicHref":"ACadSharp.Objects.ResolutionUnit.html","topicUid":"ACadSharp.Objects.ResolutionUnit","type":"Enum"},{"name":"RotatedDimensionType","href":"ACadSharp.Objects.RotatedDimensionType.html","topicHref":"ACadSharp.Objects.RotatedDimensionType.html","topicUid":"ACadSharp.Objects.RotatedDimensionType","type":"Enum"},{"name":"Scale","href":"ACadSharp.Objects.Scale.html","topicHref":"ACadSharp.Objects.Scale.html","topicUid":"ACadSharp.Objects.Scale","type":"Class"},{"name":"ScaleEstimationType","href":"ACadSharp.Objects.ScaleEstimationType.html","topicHref":"ACadSharp.Objects.ScaleEstimationType.html","topicUid":"ACadSharp.Objects.ScaleEstimationType","type":"Enum"},{"name":"ScaledType","href":"ACadSharp.Objects.ScaledType.html","topicHref":"ACadSharp.Objects.ScaledType.html","topicUid":"ACadSharp.Objects.ScaledType","type":"Enum"},{"name":"ShadePlotMode","href":"ACadSharp.Objects.ShadePlotMode.html","topicHref":"ACadSharp.Objects.ShadePlotMode.html","topicUid":"ACadSharp.Objects.ShadePlotMode","type":"Enum"},{"name":"ShadePlotResolutionMode","href":"ACadSharp.Objects.ShadePlotResolutionMode.html","topicHref":"ACadSharp.Objects.ShadePlotResolutionMode.html","topicUid":"ACadSharp.Objects.ShadePlotResolutionMode","type":"Enum"},{"name":"SortEntitiesTable","href":"ACadSharp.Objects.SortEntitiesTable.html","topicHref":"ACadSharp.Objects.SortEntitiesTable.html","topicUid":"ACadSharp.Objects.SortEntitiesTable","type":"Class"},{"name":"SortEntitiesTable.Sorter","href":"ACadSharp.Objects.SortEntitiesTable.Sorter.html","topicHref":"ACadSharp.Objects.SortEntitiesTable.Sorter.html","topicUid":"ACadSharp.Objects.SortEntitiesTable.Sorter","type":"Class"},{"name":"SpatialFilter","href":"ACadSharp.Objects.SpatialFilter.html","topicHref":"ACadSharp.Objects.SpatialFilter.html","topicUid":"ACadSharp.Objects.SpatialFilter","type":"Class"},{"name":"SubentType","href":"ACadSharp.Objects.SubentType.html","topicHref":"ACadSharp.Objects.SubentType.html","topicUid":"ACadSharp.Objects.SubentType","type":"Enum"},{"name":"TableContent","href":"ACadSharp.Objects.TableContent.html","topicHref":"ACadSharp.Objects.TableContent.html","topicUid":"ACadSharp.Objects.TableContent","type":"Class"},{"name":"TableFlowDirectionType","href":"ACadSharp.Objects.TableFlowDirectionType.html","topicHref":"ACadSharp.Objects.TableFlowDirectionType.html","topicUid":"ACadSharp.Objects.TableFlowDirectionType","type":"Enum"},{"name":"TableStyle","href":"ACadSharp.Objects.TableStyle.html","topicHref":"ACadSharp.Objects.TableStyle.html","topicUid":"ACadSharp.Objects.TableStyle","type":"Class"},{"name":"TableStyle.BorderPropertyFlags","href":"ACadSharp.Objects.TableStyle.BorderPropertyFlags.html","topicHref":"ACadSharp.Objects.TableStyle.BorderPropertyFlags.html","topicUid":"ACadSharp.Objects.TableStyle.BorderPropertyFlags","type":"Enum"},{"name":"TableStyle.BorderType","href":"ACadSharp.Objects.TableStyle.BorderType.html","topicHref":"ACadSharp.Objects.TableStyle.BorderType.html","topicUid":"ACadSharp.Objects.TableStyle.BorderType","type":"Enum"},{"name":"TableStyle.CellAlignmentType","href":"ACadSharp.Objects.TableStyle.CellAlignmentType.html","topicHref":"ACadSharp.Objects.TableStyle.CellAlignmentType.html","topicUid":"ACadSharp.Objects.TableStyle.CellAlignmentType","type":"Enum"},{"name":"TableStyle.CellBorder","href":"ACadSharp.Objects.TableStyle.CellBorder.html","topicHref":"ACadSharp.Objects.TableStyle.CellBorder.html","topicUid":"ACadSharp.Objects.TableStyle.CellBorder","type":"Class"},{"name":"TableStyle.CellContentLayoutFlags","href":"ACadSharp.Objects.TableStyle.CellContentLayoutFlags.html","topicHref":"ACadSharp.Objects.TableStyle.CellContentLayoutFlags.html","topicUid":"ACadSharp.Objects.TableStyle.CellContentLayoutFlags","type":"Enum"},{"name":"TableStyle.CellEdgeFlags","href":"ACadSharp.Objects.TableStyle.CellEdgeFlags.html","topicHref":"ACadSharp.Objects.TableStyle.CellEdgeFlags.html","topicUid":"ACadSharp.Objects.TableStyle.CellEdgeFlags","type":"Enum"},{"name":"TableStyle.CellStyle","href":"ACadSharp.Objects.TableStyle.CellStyle.html","topicHref":"ACadSharp.Objects.TableStyle.CellStyle.html","topicUid":"ACadSharp.Objects.TableStyle.CellStyle","type":"Class"},{"name":"TableStyle.CellStyleClass","href":"ACadSharp.Objects.TableStyle.CellStyleClass.html","topicHref":"ACadSharp.Objects.TableStyle.CellStyleClass.html","topicUid":"ACadSharp.Objects.TableStyle.CellStyleClass","type":"Enum"},{"name":"TableStyle.CellStylePropertyFlags","href":"ACadSharp.Objects.TableStyle.CellStylePropertyFlags.html","topicHref":"ACadSharp.Objects.TableStyle.CellStylePropertyFlags.html","topicUid":"ACadSharp.Objects.TableStyle.CellStylePropertyFlags","type":"Enum"},{"name":"TableStyle.CellStyleType","href":"ACadSharp.Objects.TableStyle.CellStyleType.html","topicHref":"ACadSharp.Objects.TableStyle.CellStyleType.html","topicUid":"ACadSharp.Objects.TableStyle.CellStyleType","type":"Enum"},{"name":"TableStyle.ContentFormat","href":"ACadSharp.Objects.TableStyle.ContentFormat.html","topicHref":"ACadSharp.Objects.TableStyle.ContentFormat.html","topicUid":"ACadSharp.Objects.TableStyle.ContentFormat","type":"Class"},{"name":"TableStyle.MarginFlags","href":"ACadSharp.Objects.TableStyle.MarginFlags.html","topicHref":"ACadSharp.Objects.TableStyle.MarginFlags.html","topicUid":"ACadSharp.Objects.TableStyle.MarginFlags","type":"Enum"},{"name":"TilingMethod","href":"ACadSharp.Objects.TilingMethod.html","topicHref":"ACadSharp.Objects.TilingMethod.html","topicUid":"ACadSharp.Objects.TilingMethod","type":"Enum"},{"name":"UnderlayDefinition","href":"ACadSharp.Objects.UnderlayDefinition.html","topicHref":"ACadSharp.Objects.UnderlayDefinition.html","topicUid":"ACadSharp.Objects.UnderlayDefinition","type":"Class"},{"name":"UnknownNonGraphicalObject","href":"ACadSharp.Objects.UnknownNonGraphicalObject.html","topicHref":"ACadSharp.Objects.UnknownNonGraphicalObject.html","topicUid":"ACadSharp.Objects.UnknownNonGraphicalObject","type":"Class"},{"name":"VisualStyle","href":"ACadSharp.Objects.VisualStyle.html","topicHref":"ACadSharp.Objects.VisualStyle.html","topicUid":"ACadSharp.Objects.VisualStyle","type":"Class"},{"name":"WipeoutFrameType","href":"ACadSharp.Objects.WipeoutFrameType.html","topicHref":"ACadSharp.Objects.WipeoutFrameType.html","topicUid":"ACadSharp.Objects.WipeoutFrameType","type":"Enum"},{"name":"XRecord","href":"ACadSharp.Objects.XRecord.html","topicHref":"ACadSharp.Objects.XRecord.html","topicUid":"ACadSharp.Objects.XRecord","type":"Class"},{"name":"XRecord.Entry","href":"ACadSharp.Objects.XRecord.Entry.html","topicHref":"ACadSharp.Objects.XRecord.Entry.html","topicUid":"ACadSharp.Objects.XRecord.Entry","type":"Class"}]},{"name":"ACadSharp.Objects.AEC","href":"ACadSharp.Objects.AEC.html","topicHref":"ACadSharp.Objects.AEC.html","topicUid":"ACadSharp.Objects.AEC","type":"Namespace","items":[{"name":"AecBinRecord","href":"ACadSharp.Objects.AEC.AecBinRecord.html","topicHref":"ACadSharp.Objects.AEC.AecBinRecord.html","topicUid":"ACadSharp.Objects.AEC.AecBinRecord","type":"Class"}]},{"name":"ACadSharp.Objects.Collections","href":"ACadSharp.Objects.Collections.html","topicHref":"ACadSharp.Objects.Collections.html","topicUid":"ACadSharp.Objects.Collections","type":"Namespace","items":[{"name":"ColorCollection","href":"ACadSharp.Objects.Collections.ColorCollection.html","topicHref":"ACadSharp.Objects.Collections.ColorCollection.html","topicUid":"ACadSharp.Objects.Collections.ColorCollection","type":"Class"},{"name":"DictionaryVariableCollection","href":"ACadSharp.Objects.Collections.DictionaryVariableCollection.html","topicHref":"ACadSharp.Objects.Collections.DictionaryVariableCollection.html","topicUid":"ACadSharp.Objects.Collections.DictionaryVariableCollection","type":"Class"},{"name":"GroupCollection","href":"ACadSharp.Objects.Collections.GroupCollection.html","topicHref":"ACadSharp.Objects.Collections.GroupCollection.html","topicUid":"ACadSharp.Objects.Collections.GroupCollection","type":"Class"},{"name":"ImageDefinitionCollection","href":"ACadSharp.Objects.Collections.ImageDefinitionCollection.html","topicHref":"ACadSharp.Objects.Collections.ImageDefinitionCollection.html","topicUid":"ACadSharp.Objects.Collections.ImageDefinitionCollection","type":"Class"},{"name":"LayoutCollection","href":"ACadSharp.Objects.Collections.LayoutCollection.html","topicHref":"ACadSharp.Objects.Collections.LayoutCollection.html","topicUid":"ACadSharp.Objects.Collections.LayoutCollection","type":"Class"},{"name":"MLeaderStyleCollection","href":"ACadSharp.Objects.Collections.MLeaderStyleCollection.html","topicHref":"ACadSharp.Objects.Collections.MLeaderStyleCollection.html","topicUid":"ACadSharp.Objects.Collections.MLeaderStyleCollection","type":"Class"},{"name":"MLineStyleCollection","href":"ACadSharp.Objects.Collections.MLineStyleCollection.html","topicHref":"ACadSharp.Objects.Collections.MLineStyleCollection.html","topicUid":"ACadSharp.Objects.Collections.MLineStyleCollection","type":"Class"},{"name":"MaterialCollection","href":"ACadSharp.Objects.Collections.MaterialCollection.html","topicHref":"ACadSharp.Objects.Collections.MaterialCollection.html","topicUid":"ACadSharp.Objects.Collections.MaterialCollection","type":"Class"},{"name":"ObjectDictionaryCollection<T>","href":"ACadSharp.Objects.Collections.ObjectDictionaryCollection-1.html","topicHref":"ACadSharp.Objects.Collections.ObjectDictionaryCollection-1.html","topicUid":"ACadSharp.Objects.Collections.ObjectDictionaryCollection`1","type":"Class"},{"name":"PdfDefinitionCollection","href":"ACadSharp.Objects.Collections.PdfDefinitionCollection.html","topicHref":"ACadSharp.Objects.Collections.PdfDefinitionCollection.html","topicUid":"ACadSharp.Objects.Collections.PdfDefinitionCollection","type":"Class"},{"name":"ScaleCollection","href":"ACadSharp.Objects.Collections.ScaleCollection.html","topicHref":"ACadSharp.Objects.Collections.ScaleCollection.html","topicUid":"ACadSharp.Objects.Collections.ScaleCollection","type":"Class"},{"name":"TableStyleCollection","href":"ACadSharp.Objects.Collections.TableStyleCollection.html","topicHref":"ACadSharp.Objects.Collections.TableStyleCollection.html","topicUid":"ACadSharp.Objects.Collections.TableStyleCollection","type":"Class"}]},{"name":"ACadSharp.Objects.Evaluations","href":"ACadSharp.Objects.Evaluations.html","topicHref":"ACadSharp.Objects.Evaluations.html","topicUid":"ACadSharp.Objects.Evaluations","type":"Namespace","items":[{"name":"Block1PtParameter","href":"ACadSharp.Objects.Evaluations.Block1PtParameter.html","topicHref":"ACadSharp.Objects.Evaluations.Block1PtParameter.html","topicUid":"ACadSharp.Objects.Evaluations.Block1PtParameter","type":"Class"},{"name":"Block2PtParameter","href":"ACadSharp.Objects.Evaluations.Block2PtParameter.html","topicHref":"ACadSharp.Objects.Evaluations.Block2PtParameter.html","topicUid":"ACadSharp.Objects.Evaluations.Block2PtParameter","type":"Class"},{"name":"BlockAction","href":"ACadSharp.Objects.Evaluations.BlockAction.html","topicHref":"ACadSharp.Objects.Evaluations.BlockAction.html","topicUid":"ACadSharp.Objects.Evaluations.BlockAction","type":"Class"},{"name":"BlockActionBasePt","href":"ACadSharp.Objects.Evaluations.BlockActionBasePt.html","topicHref":"ACadSharp.Objects.Evaluations.BlockActionBasePt.html","topicUid":"ACadSharp.Objects.Evaluations.BlockActionBasePt","type":"Class"},{"name":"BlockBasePointParameter","href":"ACadSharp.Objects.Evaluations.BlockBasePointParameter.html","topicHref":"ACadSharp.Objects.Evaluations.BlockBasePointParameter.html","topicUid":"ACadSharp.Objects.Evaluations.BlockBasePointParameter","type":"Class"},{"name":"BlockElement","href":"ACadSharp.Objects.Evaluations.BlockElement.html","topicHref":"ACadSharp.Objects.Evaluations.BlockElement.html","topicUid":"ACadSharp.Objects.Evaluations.BlockElement","type":"Class"},{"name":"BlockFlipAction","href":"ACadSharp.Objects.Evaluations.BlockFlipAction.html","topicHref":"ACadSharp.Objects.Evaluations.BlockFlipAction.html","topicUid":"ACadSharp.Objects.Evaluations.BlockFlipAction","type":"Class"},{"name":"BlockFlipGrip","href":"ACadSharp.Objects.Evaluations.BlockFlipGrip.html","topicHref":"ACadSharp.Objects.Evaluations.BlockFlipGrip.html","topicUid":"ACadSharp.Objects.Evaluations.BlockFlipGrip","type":"Class"},{"name":"BlockFlipParameter","href":"ACadSharp.Objects.Evaluations.BlockFlipParameter.html","topicHref":"ACadSharp.Objects.Evaluations.BlockFlipParameter.html","topicUid":"ACadSharp.Objects.Evaluations.BlockFlipParameter","type":"Class"},{"name":"BlockGrip","href":"ACadSharp.Objects.Evaluations.BlockGrip.html","topicHref":"ACadSharp.Objects.Evaluations.BlockGrip.html","topicUid":"ACadSharp.Objects.Evaluations.BlockGrip","type":"Class"},{"name":"BlockGripExpression","href":"ACadSharp.Objects.Evaluations.BlockGripExpression.html","topicHref":"ACadSharp.Objects.Evaluations.BlockGripExpression.html","topicUid":"ACadSharp.Objects.Evaluations.BlockGripExpression","type":"Class"},{"name":"BlockLinearParameter","href":"ACadSharp.Objects.Evaluations.BlockLinearParameter.html","topicHref":"ACadSharp.Objects.Evaluations.BlockLinearParameter.html","topicUid":"ACadSharp.Objects.Evaluations.BlockLinearParameter","type":"Class"},{"name":"BlockParameter","href":"ACadSharp.Objects.Evaluations.BlockParameter.html","topicHref":"ACadSharp.Objects.Evaluations.BlockParameter.html","topicUid":"ACadSharp.Objects.Evaluations.BlockParameter","type":"Class"},{"name":"BlockRotationAction","href":"ACadSharp.Objects.Evaluations.BlockRotationAction.html","topicHref":"ACadSharp.Objects.Evaluations.BlockRotationAction.html","topicUid":"ACadSharp.Objects.Evaluations.BlockRotationAction","type":"Class"},{"name":"BlockRotationGrip","href":"ACadSharp.Objects.Evaluations.BlockRotationGrip.html","topicHref":"ACadSharp.Objects.Evaluations.BlockRotationGrip.html","topicUid":"ACadSharp.Objects.Evaluations.BlockRotationGrip","type":"Class"},{"name":"BlockRotationParameter","href":"ACadSharp.Objects.Evaluations.BlockRotationParameter.html","topicHref":"ACadSharp.Objects.Evaluations.BlockRotationParameter.html","topicUid":"ACadSharp.Objects.Evaluations.BlockRotationParameter","type":"Class"},{"name":"BlockVisibilityGrip","href":"ACadSharp.Objects.Evaluations.BlockVisibilityGrip.html","topicHref":"ACadSharp.Objects.Evaluations.BlockVisibilityGrip.html","topicUid":"ACadSharp.Objects.Evaluations.BlockVisibilityGrip","type":"Class"},{"name":"BlockVisibilityParameter","href":"ACadSharp.Objects.Evaluations.BlockVisibilityParameter.html","topicHref":"ACadSharp.Objects.Evaluations.BlockVisibilityParameter.html","topicUid":"ACadSharp.Objects.Evaluations.BlockVisibilityParameter","type":"Class"},{"name":"BlockVisibilityParameter.State","href":"ACadSharp.Objects.Evaluations.BlockVisibilityParameter.State.html","topicHref":"ACadSharp.Objects.Evaluations.BlockVisibilityParameter.State.html","topicUid":"ACadSharp.Objects.Evaluations.BlockVisibilityParameter.State","type":"Class"},{"name":"EvaluationExpression","href":"ACadSharp.Objects.Evaluations.EvaluationExpression.html","topicHref":"ACadSharp.Objects.Evaluations.EvaluationExpression.html","topicUid":"ACadSharp.Objects.Evaluations.EvaluationExpression","type":"Class"},{"name":"EvaluationGraph","href":"ACadSharp.Objects.Evaluations.EvaluationGraph.html","topicHref":"ACadSharp.Objects.Evaluations.EvaluationGraph.html","topicUid":"ACadSharp.Objects.Evaluations.EvaluationGraph","type":"Class"},{"name":"EvaluationGraph.Edge","href":"ACadSharp.Objects.Evaluations.EvaluationGraph.Edge.html","topicHref":"ACadSharp.Objects.Evaluations.EvaluationGraph.Edge.html","topicUid":"ACadSharp.Objects.Evaluations.EvaluationGraph.Edge","type":"Class"},{"name":"EvaluationGraph.Node","href":"ACadSharp.Objects.Evaluations.EvaluationGraph.Node.html","topicHref":"ACadSharp.Objects.Evaluations.EvaluationGraph.Node.html","topicUid":"ACadSharp.Objects.Evaluations.EvaluationGraph.Node","type":"Class"}]},{"name":"ACadSharp.Tables","href":"ACadSharp.Tables.html","topicHref":"ACadSharp.Tables.html","topicUid":"ACadSharp.Tables","type":"Namespace","items":[{"name":"AngularZeroHandling","href":"ACadSharp.Tables.AngularZeroHandling.html","topicHref":"ACadSharp.Tables.AngularZeroHandling.html","topicUid":"ACadSharp.Tables.AngularZeroHandling","type":"Enum"},{"name":"AppId","href":"ACadSharp.Tables.AppId.html","topicHref":"ACadSharp.Tables.AppId.html","topicUid":"ACadSharp.Tables.AppId","type":"Class"},{"name":"ArcLengthSymbolPosition","href":"ACadSharp.Tables.ArcLengthSymbolPosition.html","topicHref":"ACadSharp.Tables.ArcLengthSymbolPosition.html","topicUid":"ACadSharp.Tables.ArcLengthSymbolPosition","type":"Enum"},{"name":"BlockRecord","href":"ACadSharp.Tables.BlockRecord.html","topicHref":"ACadSharp.Tables.BlockRecord.html","topicUid":"ACadSharp.Tables.BlockRecord","type":"Class"},{"name":"DefaultLightingType","href":"ACadSharp.Tables.DefaultLightingType.html","topicHref":"ACadSharp.Tables.DefaultLightingType.html","topicUid":"ACadSharp.Tables.DefaultLightingType","type":"Enum"},{"name":"DimensionStyle","href":"ACadSharp.Tables.DimensionStyle.html","topicHref":"ACadSharp.Tables.DimensionStyle.html","topicUid":"ACadSharp.Tables.DimensionStyle","type":"Class"},{"name":"DimensionTextBackgroundFillMode","href":"ACadSharp.Tables.DimensionTextBackgroundFillMode.html","topicHref":"ACadSharp.Tables.DimensionTextBackgroundFillMode.html","topicUid":"ACadSharp.Tables.DimensionTextBackgroundFillMode","type":"Enum"},{"name":"DimensionTextHorizontalAlignment","href":"ACadSharp.Tables.DimensionTextHorizontalAlignment.html","topicHref":"ACadSharp.Tables.DimensionTextHorizontalAlignment.html","topicUid":"ACadSharp.Tables.DimensionTextHorizontalAlignment","type":"Enum"},{"name":"DimensionTextVerticalAlignment","href":"ACadSharp.Tables.DimensionTextVerticalAlignment.html","topicHref":"ACadSharp.Tables.DimensionTextVerticalAlignment.html","topicUid":"ACadSharp.Tables.DimensionTextVerticalAlignment","type":"Enum"},{"name":"EntryFlags","href":"ACadSharp.Tables.EntryFlags.html","topicHref":"ACadSharp.Tables.EntryFlags.html","topicUid":"ACadSharp.Tables.EntryFlags","type":"Enum"},{"name":"FontFlags","href":"ACadSharp.Tables.FontFlags.html","topicHref":"ACadSharp.Tables.FontFlags.html","topicUid":"ACadSharp.Tables.FontFlags","type":"Enum"},{"name":"FractionFormat","href":"ACadSharp.Tables.FractionFormat.html","topicHref":"ACadSharp.Tables.FractionFormat.html","topicUid":"ACadSharp.Tables.FractionFormat","type":"Enum"},{"name":"GridFlags","href":"ACadSharp.Tables.GridFlags.html","topicHref":"ACadSharp.Tables.GridFlags.html","topicUid":"ACadSharp.Tables.GridFlags","type":"Enum"},{"name":"Layer","href":"ACadSharp.Tables.Layer.html","topicHref":"ACadSharp.Tables.Layer.html","topicUid":"ACadSharp.Tables.Layer","type":"Class"},{"name":"LayerFlags","href":"ACadSharp.Tables.LayerFlags.html","topicHref":"ACadSharp.Tables.LayerFlags.html","topicUid":"ACadSharp.Tables.LayerFlags","type":"Enum"},{"name":"LineType","href":"ACadSharp.Tables.LineType.html","topicHref":"ACadSharp.Tables.LineType.html","topicUid":"ACadSharp.Tables.LineType","type":"Class"},{"name":"LineType.Segment","href":"ACadSharp.Tables.LineType.Segment.html","topicHref":"ACadSharp.Tables.LineType.Segment.html","topicUid":"ACadSharp.Tables.LineType.Segment","type":"Class"},{"name":"LineTypeShapeFlags","href":"ACadSharp.Tables.LineTypeShapeFlags.html","topicHref":"ACadSharp.Tables.LineTypeShapeFlags.html","topicUid":"ACadSharp.Tables.LineTypeShapeFlags","type":"Enum"},{"name":"StandardFlags","href":"ACadSharp.Tables.StandardFlags.html","topicHref":"ACadSharp.Tables.StandardFlags.html","topicUid":"ACadSharp.Tables.StandardFlags","type":"Enum"},{"name":"StyleFlags","href":"ACadSharp.Tables.StyleFlags.html","topicHref":"ACadSharp.Tables.StyleFlags.html","topicUid":"ACadSharp.Tables.StyleFlags","type":"Enum"},{"name":"TableEntry","href":"ACadSharp.Tables.TableEntry.html","topicHref":"ACadSharp.Tables.TableEntry.html","topicUid":"ACadSharp.Tables.TableEntry","type":"Class"},{"name":"TextArrowFitType","href":"ACadSharp.Tables.TextArrowFitType.html","topicHref":"ACadSharp.Tables.TextArrowFitType.html","topicUid":"ACadSharp.Tables.TextArrowFitType","type":"Enum"},{"name":"TextDirection","href":"ACadSharp.Tables.TextDirection.html","topicHref":"ACadSharp.Tables.TextDirection.html","topicUid":"ACadSharp.Tables.TextDirection","type":"Enum"},{"name":"TextMovement","href":"ACadSharp.Tables.TextMovement.html","topicHref":"ACadSharp.Tables.TextMovement.html","topicUid":"ACadSharp.Tables.TextMovement","type":"Enum"},{"name":"TextStyle","href":"ACadSharp.Tables.TextStyle.html","topicHref":"ACadSharp.Tables.TextStyle.html","topicUid":"ACadSharp.Tables.TextStyle","type":"Class"},{"name":"ToleranceAlignment","href":"ACadSharp.Tables.ToleranceAlignment.html","topicHref":"ACadSharp.Tables.ToleranceAlignment.html","topicUid":"ACadSharp.Tables.ToleranceAlignment","type":"Enum"},{"name":"UCS","href":"ACadSharp.Tables.UCS.html","topicHref":"ACadSharp.Tables.UCS.html","topicUid":"ACadSharp.Tables.UCS","type":"Class"},{"name":"UscIconType","href":"ACadSharp.Tables.UscIconType.html","topicHref":"ACadSharp.Tables.UscIconType.html","topicUid":"ACadSharp.Tables.UscIconType","type":"Enum"},{"name":"VPort","href":"ACadSharp.Tables.VPort.html","topicHref":"ACadSharp.Tables.VPort.html","topicUid":"ACadSharp.Tables.VPort","type":"Class"},{"name":"View","href":"ACadSharp.Tables.View.html","topicHref":"ACadSharp.Tables.View.html","topicUid":"ACadSharp.Tables.View","type":"Class"},{"name":"ViewModeType","href":"ACadSharp.Tables.ViewModeType.html","topicHref":"ACadSharp.Tables.ViewModeType.html","topicUid":"ACadSharp.Tables.ViewModeType","type":"Enum"},{"name":"ZeroHandling","href":"ACadSharp.Tables.ZeroHandling.html","topicHref":"ACadSharp.Tables.ZeroHandling.html","topicUid":"ACadSharp.Tables.ZeroHandling","type":"Enum"}]},{"name":"ACadSharp.Tables.Collections","href":"ACadSharp.Tables.Collections.html","topicHref":"ACadSharp.Tables.Collections.html","topicUid":"ACadSharp.Tables.Collections","type":"Namespace","items":[{"name":"AppIdsTable","href":"ACadSharp.Tables.Collections.AppIdsTable.html","topicHref":"ACadSharp.Tables.Collections.AppIdsTable.html","topicUid":"ACadSharp.Tables.Collections.AppIdsTable","type":"Class"},{"name":"BlockRecordsTable","href":"ACadSharp.Tables.Collections.BlockRecordsTable.html","topicHref":"ACadSharp.Tables.Collections.BlockRecordsTable.html","topicUid":"ACadSharp.Tables.Collections.BlockRecordsTable","type":"Class"},{"name":"DimensionStylesTable","href":"ACadSharp.Tables.Collections.DimensionStylesTable.html","topicHref":"ACadSharp.Tables.Collections.DimensionStylesTable.html","topicUid":"ACadSharp.Tables.Collections.DimensionStylesTable","type":"Class"},{"name":"ITable","href":"ACadSharp.Tables.Collections.ITable.html","topicHref":"ACadSharp.Tables.Collections.ITable.html","topicUid":"ACadSharp.Tables.Collections.ITable","type":"Interface"},{"name":"LayersTable","href":"ACadSharp.Tables.Collections.LayersTable.html","topicHref":"ACadSharp.Tables.Collections.LayersTable.html","topicUid":"ACadSharp.Tables.Collections.LayersTable","type":"Class"},{"name":"LineTypesTable","href":"ACadSharp.Tables.Collections.LineTypesTable.html","topicHref":"ACadSharp.Tables.Collections.LineTypesTable.html","topicUid":"ACadSharp.Tables.Collections.LineTypesTable","type":"Class"},{"name":"Table<T>","href":"ACadSharp.Tables.Collections.Table-1.html","topicHref":"ACadSharp.Tables.Collections.Table-1.html","topicUid":"ACadSharp.Tables.Collections.Table`1","type":"Class"},{"name":"TextStylesTable","href":"ACadSharp.Tables.Collections.TextStylesTable.html","topicHref":"ACadSharp.Tables.Collections.TextStylesTable.html","topicUid":"ACadSharp.Tables.Collections.TextStylesTable","type":"Class"},{"name":"UCSTable","href":"ACadSharp.Tables.Collections.UCSTable.html","topicHref":"ACadSharp.Tables.Collections.UCSTable.html","topicUid":"ACadSharp.Tables.Collections.UCSTable","type":"Class"},{"name":"VPortsTable","href":"ACadSharp.Tables.Collections.VPortsTable.html","topicHref":"ACadSharp.Tables.Collections.VPortsTable.html","topicUid":"ACadSharp.Tables.Collections.VPortsTable","type":"Class"},{"name":"ViewsTable","href":"ACadSharp.Tables.Collections.ViewsTable.html","topicHref":"ACadSharp.Tables.Collections.ViewsTable.html","topicUid":"ACadSharp.Tables.Collections.ViewsTable","type":"Class"}]},{"name":"ACadSharp.Text","href":"ACadSharp.Text.html","topicHref":"ACadSharp.Text.html","topicUid":"ACadSharp.Text","type":"Namespace","items":[{"name":"TextProcessor","href":"ACadSharp.Text.TextProcessor.html","topicHref":"ACadSharp.Text.TextProcessor.html","topicUid":"ACadSharp.Text.TextProcessor","type":"Class"}]},{"name":"ACadSharp.Types.Units","href":"ACadSharp.Types.Units.html","topicHref":"ACadSharp.Types.Units.html","topicUid":"ACadSharp.Types.Units","type":"Namespace","items":[{"name":"AngularDirection","href":"ACadSharp.Types.Units.AngularDirection.html","topicHref":"ACadSharp.Types.Units.AngularDirection.html","topicUid":"ACadSharp.Types.Units.AngularDirection","type":"Enum"},{"name":"AngularUnitFormat","href":"ACadSharp.Types.Units.AngularUnitFormat.html","topicHref":"ACadSharp.Types.Units.AngularUnitFormat.html","topicUid":"ACadSharp.Types.Units.AngularUnitFormat","type":"Enum"},{"name":"ImageUnits","href":"ACadSharp.Types.Units.ImageUnits.html","topicHref":"ACadSharp.Types.Units.ImageUnits.html","topicUid":"ACadSharp.Types.Units.ImageUnits","type":"Enum"},{"name":"LinearUnitFormat","href":"ACadSharp.Types.Units.LinearUnitFormat.html","topicHref":"ACadSharp.Types.Units.LinearUnitFormat.html","topicUid":"ACadSharp.Types.Units.LinearUnitFormat","type":"Enum"},{"name":"UnitStyleFormat","href":"ACadSharp.Types.Units.UnitStyleFormat.html","topicHref":"ACadSharp.Types.Units.UnitStyleFormat.html","topicUid":"ACadSharp.Types.Units.UnitStyleFormat","type":"Class"},{"name":"UnitsType","href":"ACadSharp.Types.Units.UnitsType.html","topicHref":"ACadSharp.Types.Units.UnitsType.html","topicUid":"ACadSharp.Types.Units.UnitsType","type":"Enum"}]},{"name":"ACadSharp.XData","href":"ACadSharp.XData.html","topicHref":"ACadSharp.XData.html","topicUid":"ACadSharp.XData","type":"Namespace","items":[{"name":"ExtendedData","href":"ACadSharp.XData.ExtendedData.html","topicHref":"ACadSharp.XData.ExtendedData.html","topicUid":"ACadSharp.XData.ExtendedData","type":"Class"},{"name":"ExtendedDataBinaryChunk","href":"ACadSharp.XData.ExtendedDataBinaryChunk.html","topicHref":"ACadSharp.XData.ExtendedDataBinaryChunk.html","topicUid":"ACadSharp.XData.ExtendedDataBinaryChunk","type":"Class"},{"name":"ExtendedDataControlString","href":"ACadSharp.XData.ExtendedDataControlString.html","topicHref":"ACadSharp.XData.ExtendedDataControlString.html","topicUid":"ACadSharp.XData.ExtendedDataControlString","type":"Class"},{"name":"ExtendedDataCoordinate","href":"ACadSharp.XData.ExtendedDataCoordinate.html","topicHref":"ACadSharp.XData.ExtendedDataCoordinate.html","topicUid":"ACadSharp.XData.ExtendedDataCoordinate","type":"Class"},{"name":"ExtendedDataDictionary","href":"ACadSharp.XData.ExtendedDataDictionary.html","topicHref":"ACadSharp.XData.ExtendedDataDictionary.html","topicUid":"ACadSharp.XData.ExtendedDataDictionary","type":"Class"},{"name":"ExtendedDataDirection","href":"ACadSharp.XData.ExtendedDataDirection.html","topicHref":"ACadSharp.XData.ExtendedDataDirection.html","topicUid":"ACadSharp.XData.ExtendedDataDirection","type":"Class"},{"name":"ExtendedDataDisplacement","href":"ACadSharp.XData.ExtendedDataDisplacement.html","topicHref":"ACadSharp.XData.ExtendedDataDisplacement.html","topicUid":"ACadSharp.XData.ExtendedDataDisplacement","type":"Class"},{"name":"ExtendedDataDistance","href":"ACadSharp.XData.ExtendedDataDistance.html","topicHref":"ACadSharp.XData.ExtendedDataDistance.html","topicUid":"ACadSharp.XData.ExtendedDataDistance","type":"Class"},{"name":"ExtendedDataHandle","href":"ACadSharp.XData.ExtendedDataHandle.html","topicHref":"ACadSharp.XData.ExtendedDataHandle.html","topicUid":"ACadSharp.XData.ExtendedDataHandle","type":"Class"},{"name":"ExtendedDataInteger16","href":"ACadSharp.XData.ExtendedDataInteger16.html","topicHref":"ACadSharp.XData.ExtendedDataInteger16.html","topicUid":"ACadSharp.XData.ExtendedDataInteger16","type":"Class"},{"name":"ExtendedDataInteger32","href":"ACadSharp.XData.ExtendedDataInteger32.html","topicHref":"ACadSharp.XData.ExtendedDataInteger32.html","topicUid":"ACadSharp.XData.ExtendedDataInteger32","type":"Class"},{"name":"ExtendedDataLayer","href":"ACadSharp.XData.ExtendedDataLayer.html","topicHref":"ACadSharp.XData.ExtendedDataLayer.html","topicUid":"ACadSharp.XData.ExtendedDataLayer","type":"Class"},{"name":"ExtendedDataReal","href":"ACadSharp.XData.ExtendedDataReal.html","topicHref":"ACadSharp.XData.ExtendedDataReal.html","topicUid":"ACadSharp.XData.ExtendedDataReal","type":"Class"},{"name":"ExtendedDataRecord","href":"ACadSharp.XData.ExtendedDataRecord.html","topicHref":"ACadSharp.XData.ExtendedDataRecord.html","topicUid":"ACadSharp.XData.ExtendedDataRecord","type":"Class"},{"name":"ExtendedDataRecord<T>","href":"ACadSharp.XData.ExtendedDataRecord-1.html","topicHref":"ACadSharp.XData.ExtendedDataRecord-1.html","topicUid":"ACadSharp.XData.ExtendedDataRecord`1","type":"Class"},{"name":"ExtendedDataReference<T>","href":"ACadSharp.XData.ExtendedDataReference-1.html","topicHref":"ACadSharp.XData.ExtendedDataReference-1.html","topicUid":"ACadSharp.XData.ExtendedDataReference`1","type":"Class"},{"name":"ExtendedDataScale","href":"ACadSharp.XData.ExtendedDataScale.html","topicHref":"ACadSharp.XData.ExtendedDataScale.html","topicUid":"ACadSharp.XData.ExtendedDataScale","type":"Class"},{"name":"ExtendedDataString","href":"ACadSharp.XData.ExtendedDataString.html","topicHref":"ACadSharp.XData.ExtendedDataString.html","topicUid":"ACadSharp.XData.ExtendedDataString","type":"Class"},{"name":"ExtendedDataWorldCoordinate","href":"ACadSharp.XData.ExtendedDataWorldCoordinate.html","topicHref":"ACadSharp.XData.ExtendedDataWorldCoordinate.html","topicUid":"ACadSharp.XData.ExtendedDataWorldCoordinate","type":"Class"},{"name":"IExtendedDataHandleReference","href":"ACadSharp.XData.IExtendedDataHandleReference.html","topicHref":"ACadSharp.XData.IExtendedDataHandleReference.html","topicUid":"ACadSharp.XData.IExtendedDataHandleReference","type":"Interface"}]},{"name":"CSMath","href":"CSMath.html","topicHref":"CSMath.html","topicUid":"CSMath","type":"Namespace","items":[{"name":"BoundingBox","href":"CSMath.BoundingBox.html","topicHref":"CSMath.BoundingBox.html","topicUid":"CSMath.BoundingBox","type":"Struct"},{"name":"BoundingBoxExtent","href":"CSMath.BoundingBoxExtent.html","topicHref":"CSMath.BoundingBoxExtent.html","topicUid":"CSMath.BoundingBoxExtent","type":"Enum"},{"name":"IVector","href":"CSMath.IVector.html","topicHref":"CSMath.IVector.html","topicUid":"CSMath.IVector","type":"Interface"},{"name":"MathHelper","href":"CSMath.MathHelper.html","topicHref":"CSMath.MathHelper.html","topicUid":"CSMath.MathHelper","type":"Class"},{"name":"Matrix3","href":"CSMath.Matrix3.html","topicHref":"CSMath.Matrix3.html","topicUid":"CSMath.Matrix3","type":"Struct"},{"name":"Matrix4","href":"CSMath.Matrix4.html","topicHref":"CSMath.Matrix4.html","topicUid":"CSMath.Matrix4","type":"Struct"},{"name":"Quaternion","href":"CSMath.Quaternion.html","topicHref":"CSMath.Quaternion.html","topicUid":"CSMath.Quaternion","type":"Struct"},{"name":"Transform","href":"CSMath.Transform.html","topicHref":"CSMath.Transform.html","topicUid":"CSMath.Transform","type":"Class"},{"name":"VectorExtensions","href":"CSMath.VectorExtensions.html","topicHref":"CSMath.VectorExtensions.html","topicUid":"CSMath.VectorExtensions","type":"Class"},{"name":"XY","href":"CSMath.XY.html","topicHref":"CSMath.XY.html","topicUid":"CSMath.XY","type":"Struct"},{"name":"XYZ","href":"CSMath.XYZ.html","topicHref":"CSMath.XYZ.html","topicUid":"CSMath.XYZ","type":"Struct"},{"name":"XYZM","href":"CSMath.XYZM.html","topicHref":"CSMath.XYZM.html","topicUid":"CSMath.XYZM","type":"Struct"}]},{"name":"CSMath.Geometry","href":"CSMath.Geometry.html","topicHref":"CSMath.Geometry.html","topicUid":"CSMath.Geometry","type":"Namespace","items":[{"name":"CurveExtensions","href":"CSMath.Geometry.CurveExtensions.html","topicHref":"CSMath.Geometry.CurveExtensions.html","topicUid":"CSMath.Geometry.CurveExtensions","type":"Class"},{"name":"ICurve","href":"CSMath.Geometry.ICurve.html","topicHref":"CSMath.Geometry.ICurve.html","topicUid":"CSMath.Geometry.ICurve","type":"Interface"},{"name":"ILine<T>","href":"CSMath.Geometry.ILine-1.html","topicHref":"CSMath.Geometry.ILine-1.html","topicUid":"CSMath.Geometry.ILine`1","type":"Interface"},{"name":"Line2D","href":"CSMath.Geometry.Line2D.html","topicHref":"CSMath.Geometry.Line2D.html","topicUid":"CSMath.Geometry.Line2D","type":"Struct"},{"name":"Line3D","href":"CSMath.Geometry.Line3D.html","topicHref":"CSMath.Geometry.Line3D.html","topicUid":"CSMath.Geometry.Line3D","type":"Struct"},{"name":"LineExtensions","href":"CSMath.Geometry.LineExtensions.html","topicHref":"CSMath.Geometry.LineExtensions.html","topicUid":"CSMath.Geometry.LineExtensions","type":"Class"}]},{"name":"CSUtilities.Attributes","href":"CSUtilities.Attributes.html","topicHref":"CSUtilities.Attributes.html","topicUid":"CSUtilities.Attributes","type":"Namespace","items":[{"name":"StringValueAttribute","href":"CSUtilities.Attributes.StringValueAttribute.html","topicHref":"CSUtilities.Attributes.StringValueAttribute.html","topicUid":"CSUtilities.Attributes.StringValueAttribute","type":"Class"}]},{"name":"CSUtilities.Extensions","href":"CSUtilities.Extensions.html","topicHref":"CSUtilities.Extensions.html","topicUid":"CSUtilities.Extensions","type":"Namespace","items":[{"name":"IDictionaryExtension","href":"CSUtilities.Extensions.IDictionaryExtension.html","topicHref":"CSUtilities.Extensions.IDictionaryExtension.html","topicUid":"CSUtilities.Extensions.IDictionaryExtension","type":"Class"}]}],"memberLayout":"SamePage"}
